Workbook

Sheet How to use
A1: How to use this workbook (Alpha set: 128 cards)
A3: Cards tab: one row per card. Fill in the blue effect columns (I–W); Value, Budget, Difference and Status calculate automatically.
A4: • Budget = (Cost × points per energy + base value + rarity bonus), × exhaust multiplier if the card exhausts.
A5: • Value = sum of each effect × its price (Rules tab), + Retain value if the card Retains. Power cards list their per-turn effect and are multiplied by the power multiplier.
A6: • 'Other value' is for unique effects the price list can't capture. Cards marked PLAYTEST in Notes rely on it, so balance those by playing.
A7: • Status: Balanced (within tolerance), Over budget, Under budget. Starter cards stay under budget so every reward feels like an upgrade.
A8: • Legendary rows are shaded. Legendaries are Unique (one copy per deck).
A9: • To add a card: type it into the first empty row below the set. Formulas are already there.
A11: Rules tab: combat numbers, budget formula and effect prices. Summary: counts by archetype and rarity, balance status, reward odds.
A12: Keywords: rules text for every keyword. New Mechanics: what needs new code before these cards work in the game.
A14: Cards C01–C20, U01–U14, R01–R06 and the starters are unchanged from v1 (already in the game). Everything else is new in the alpha set.
A16: Example row: C01 Slash — Attack, cost 1, Common, Damage 9 → Value 9, Budget 9, Balanced.

Sheet Rules
A1: Dungeon Roguelike – Balance Rules (Alpha set, 128 cards)
A2: Blue cells on yellow are inputs: change them and every card's value/budget on the Cards tab recalculates.
A4: Baseline (combat)
A5: Player max HP | B5: 70 | C5: Starting value; tune in playtests
A6: Energy per turn | B6: 3
A7: Cards drawn per turn | B7: 5
A8: Starter deck size | B8: 10 | C8: 5 Strike, 4 Defend, 1 Lantern Bash
A9: Normal enemy HP (min) | B9: 12 | C9: Simulation: fights last ~2 turns at 12-25 HP; ~35-45 would hit the 3-4 turn target
A10: Normal enemy HP (max) | B10: 25
A11: Elite HP (min) | B11: 40
A12: Elite HP (max) | B12: 60
A13: Boss HP | B13: 130 | C13: Single boss for v1
A15: Budget formula
A16: Points per energy | B16: 6 | C16: Budget = cost × this + base + rarity bonus
A17: Base card value | B17: 3 | C17: Being a card is worth something (draw + hand slot)
A18: Rarity bonus: Common | B18: 0
A19: Rarity bonus: Uncommon | B19: 2
A20: Rarity bonus: Rare | B20: 4
A21: Rarity bonus: Legendary | B21: 6 | C21: NEW. Legendaries are also Unique: one copy per deck
A22: Exhaust budget multiplier | B22: 1.3 | C22: One-use cards get 30% more budget
A23: Power value multiplier | B23: 2 | C23: Power effects listed per turn are worth ×2
A24: 'All enemies' multiplier | B24: 1.5 | C24: Applies to AoE damage and debuffs that hit all enemies
A25: Balanced tolerance (±) | B25: 1.5 | C25: Value within this of budget = Balanced
A27: Effect price list (points per 1)
A28: Damage | B28: 1
A29: Block | B29: 1.2 | C29: Reliable defense is slightly better than damage
A30: Heal | B30: 1.5 | C30: Healing is scarce in roguelikes; keep it pricey
A31: Draw | B31: 4
A32: Energy | B32: 6 | C32: Also used for 'next turn, gain energy'
A33: Weak (per turn) | B33: 3 | C33: Enemy deals 25% less damage
A34: Vulnerable (per turn) | B34: 3 | C34: Enemy takes 50% more damage
A35: Poison (per stack) | B35: 1.5
A36: Strength (per stack) | B36: 4 | C36: +1 damage per attack hit for the rest of the fight
A37: HP loss (per 1) | B37: 1.5 | C37: A cost to the player; subtracts value
A38: Retain | B38: 2 | C38: NEW. Flat value for a card that stays in your hand

Sheet Cards
A1: ID | B1: Name | C1: Type | D1: Cost | E1: Rarity | F1: Archetype | G1: Card text | H1: Upgraded text | I1: Damage | J1: AoE dmg | K1: Block | L1: Heal | M1: Draw | N1: Energy | O1: Weak | P1: Vuln | Q1: Poison | R1: Debuffs hit all? | S1: Strength | T1: HP loss | U1: Exhaust? | V1: Retain? | W1: Other value | X1: Notes | Y1: Value | Z1: Budget | AA1: Difference | AB1: Status
A2: S01 | B2: Strike | C2: Attack | D2: 1 | E2: Starter | F2: Neutral | G2: Deal 6 damage. | H2: Deal 9 damage. | I2: 6 | X2: x5 in starter deck | Y2: =ROUND((I2*Rules!$B$28+J2*Rules!$B$28*Rules!$B$24+K2*Rules!$B$29+L2*Rules!$B$30+M2*Rules!$B$31+N2*Rules!$B$32+(O2*Rules!$B$33+P2*Rules!$B$34+Q2*Rules!$B$35)*IF(R2="Y",Rules!$B$24,1)+S2*Rules!$B$36-T2*Rules!$B$37+IF(V2="Y",Rules!$B$38,0)+W2)*IF(C2="Power",Rules!$B$23,1),2) -> 6 | Z2: =ROUND((D2*Rules!$B$16+Rules!$B$17+IF(E2="Legendary",Rules!$B$21,IF(E2="Rare",Rules!$B$20,IF(E2="Uncommon",Rules!$B$19,Rules!$B$18))))*IF(U2="Y",Rules!$B$22,1),2) -> 9 | AA2: =Y2-Z2 -> -3 | AB2: =IF(E2="Starter",IF(AA2<0,"Starter (under on purpose)","Starter too strong"),IF(ABS(AA2)<=Rules!$B$25,"Balanced",IF(AA2>0,"Over budget","Under budget"))) -> Starter (under on purpose)
A3: S02 | B3: Defend | C3: Skill | D3: 1 | E3: Starter | F3: Neutral | G3: Gain 5 block. | H3: Gain 8 block. | K3: 5 | X3: x4 in starter deck | Y3: =ROUND((I3*Rules!$B$28+J3*Rules!$B$28*Rules!$B$24+K3*Rules!$B$29+L3*Rules!$B$30+M3*Rules!$B$31+N3*Rules!$B$32+(O3*Rules!$B$33+P3*Rules!$B$34+Q3*Rules!$B$35)*IF(R3="Y",Rules!$B$24,1)+S3*Rules!$B$36-T3*Rules!$B$37+IF(V3="Y",Rules!$B$38,0)+W3)*IF(C3="Power",Rules!$B$23,1),2) -> 6 | Z3: =ROUND((D3*Rules!$B$16+Rules!$B$17+IF(E3="Legendary",Rules!$B$21,IF(E3="Rare",Rules!$B$20,IF(E3="Uncommon",Rules!$B$19,Rules!$B$18))))*IF(U3="Y",Rules!$B$22,1),2) -> 9 | AA3: =Y3-Z3 -> -3 | AB3: =IF(E3="Starter",IF(AA3<0,"Starter (under on purpose)","Starter too strong"),IF(ABS(AA3)<=Rules!$B$25,"Balanced",IF(AA3>0,"Over budget","Under budget"))) -> Starter (under on purpose)
A4: S03 | B4: Lantern Bash | C4: Attack | D4: 1 | E4: Starter | F4: Neutral | G4: Deal 5 damage. Apply 1 Vulnerable. | H4: Deal 7 damage. Apply 2 Vulnerable. | I4: 5 | P4: 1 | X4: x1 signature card; teaches debuffs | Y4: =ROUND((I4*Rules!$B$28+J4*Rules!$B$28*Rules!$B$24+K4*Rules!$B$29+L4*Rules!$B$30+M4*Rules!$B$31+N4*Rules!$B$32+(O4*Rules!$B$33+P4*Rules!$B$34+Q4*Rules!$B$35)*IF(R4="Y",Rules!$B$24,1)+S4*Rules!$B$36-T4*Rules!$B$37+IF(V4="Y",Rules!$B$38,0)+W4)*IF(C4="Power",Rules!$B$23,1),2) -> 8 | Z4: =ROUND((D4*Rules!$B$16+Rules!$B$17+IF(E4="Legendary",Rules!$B$21,IF(E4="Rare",Rules!$B$20,IF(E4="Uncommon",Rules!$B$19,Rules!$B$18))))*IF(U4="Y",Rules!$B$22,1),2) -> 9 | AA4: =Y4-Z4 -> -1 | AB4: =IF(E4="Starter",IF(AA4<0,"Starter (under on purpose)","Starter too strong"),IF(ABS(AA4)<=Rules!$B$25,"Balanced",IF(AA4>0,"Over budget","Under budget"))) -> Starter (under on purpose)
A5: C01 | B5: Slash | C5: Attack | D5: 1 | E5: Common | F5: Neutral | G5: Deal 9 damage. | H5: Deal 12 damage. | I5: 9 | Y5: =ROUND((I5*Rules!$B$28+J5*Rules!$B$28*Rules!$B$24+K5*Rules!$B$29+L5*Rules!$B$30+M5*Rules!$B$31+N5*Rules!$B$32+(O5*Rules!$B$33+P5*Rules!$B$34+Q5*Rules!$B$35)*IF(R5="Y",Rules!$B$24,1)+S5*Rules!$B$36-T5*Rules!$B$37+IF(V5="Y",Rules!$B$38,0)+W5)*IF(C5="Power",Rules!$B$23,1),2) -> 9 | Z5: =ROUND((D5*Rules!$B$16+Rules!$B$17+IF(E5="Legendary",Rules!$B$21,IF(E5="Rare",Rules!$B$20,IF(E5="Uncommon",Rules!$B$19,Rules!$B$18))))*IF(U5="Y",Rules!$B$22,1),2) -> 9 | AA5: =Y5-Z5 -> 0 | AB5: =IF(E5="Starter",IF(AA5<0,"Starter (under on purpose)","Starter too strong"),IF(ABS(AA5)<=Rules!$B$25,"Balanced",IF(AA5>0,"Over budget","Under budget"))) -> Balanced
A6: C02 | B6: Quick Jab | C6: Attack | D6: 0 | E6: Common | F6: Brawler | G6: Deal 3 damage. | H6: Deal 5 damage. | I6: 3 | X6: Free attacks scale with Strength | Y6: =ROUND((I6*Rules!$B$28+J6*Rules!$B$28*Rules!$B$24+K6*Rules!$B$29+L6*Rules!$B$30+M6*Rules!$B$31+N6*Rules!$B$32+(O6*Rules!$B$33+P6*Rules!$B$34+Q6*Rules!$B$35)*IF(R6="Y",Rules!$B$24,1)+S6*Rules!$B$36-T6*Rules!$B$37+IF(V6="Y",Rules!$B$38,0)+W6)*IF(C6="Power",Rules!$B$23,1),2) -> 3 | Z6: =ROUND((D6*Rules!$B$16+Rules!$B$17+IF(E6="Legendary",Rules!$B$21,IF(E6="Rare",Rules!$B$20,IF(E6="Uncommon",Rules!$B$19,Rules!$B$18))))*IF(U6="Y",Rules!$B$22,1),2) -> 3 | AA6: =Y6-Z6 -> 0 | AB6: =IF(E6="Starter",IF(AA6<0,"Starter (under on purpose)","Starter too strong"),IF(ABS(AA6)<=Rules!$B$25,"Balanced",IF(AA6>0,"Over budget","Under budget"))) -> Balanced
A7: C03 | B7: Cleave | C7: Attack | D7: 1 | E7: Common | F7: Neutral | G7: Deal 6 damage to ALL enemies. | H7: Deal 9 damage to ALL enemies. | J7: 6 | Y7: =ROUND((I7*Rules!$B$28+J7*Rules!$B$28*Rules!$B$24+K7*Rules!$B$29+L7*Rules!$B$30+M7*Rules!$B$31+N7*Rules!$B$32+(O7*Rules!$B$33+P7*Rules!$B$34+Q7*Rules!$B$35)*IF(R7="Y",Rules!$B$24,1)+S7*Rules!$B$36-T7*Rules!$B$37+IF(V7="Y",Rules!$B$38,0)+W7)*IF(C7="Power",Rules!$B$23,1),2) -> 9 | Z7: =ROUND((D7*Rules!$B$16+Rules!$B$17+IF(E7="Legendary",Rules!$B$21,IF(E7="Rare",Rules!$B$20,IF(E7="Uncommon",Rules!$B$19,Rules!$B$18))))*IF(U7="Y",Rules!$B$22,1),2) -> 9 | AA7: =Y7-Z7 -> 0 | AB7: =IF(E7="Starter",IF(AA7<0,"Starter (under on purpose)","Starter too strong"),IF(ABS(AA7)<=Rules!$B$25,"Balanced",IF(AA7>0,"Over budget","Under budget"))) -> Balanced
A8: C04 | B8: Heavy Swing | C8: Attack | D8: 2 | E8: Common | F8: Brawler | G8: Deal 15 damage. | H8: Deal 20 damage. | I8: 15 | Y8: =ROUND((I8*Rules!$B$28+J8*Rules!$B$28*Rules!$B$24+K8*Rules!$B$29+L8*Rules!$B$30+M8*Rules!$B$31+N8*Rules!$B$32+(O8*Rules!$B$33+P8*Rules!$B$34+Q8*Rules!$B$35)*IF(R8="Y",Rules!$B$24,1)+S8*Rules!$B$36-T8*Rules!$B$37+IF(V8="Y",Rules!$B$38,0)+W8)*IF(C8="Power",Rules!$B$23,1),2) -> 15 | Z8: =ROUND((D8*Rules!$B$16+Rules!$B$17+IF(E8="Legendary",Rules!$B$21,IF(E8="Rare",Rules!$B$20,IF(E8="Uncommon",Rules!$B$19,Rules!$B$18))))*IF(U8="Y",Rules!$B$22,1),2) -> 15 | AA8: =Y8-Z8 -> 0 | AB8: =IF(E8="Starter",IF(AA8<0,"Starter (under on purpose)","Starter too strong"),IF(ABS(AA8)<=Rules!$B$25,"Balanced",IF(AA8>0,"Over budget","Under budget"))) -> Balanced
A9: C05 | B9: Twin Strike | C9: Attack | D9: 1 | E9: Common | F9: Brawler | G9: Deal 4 damage twice. | H9: Deal 5 damage twice. | I9: 8 | W9: 1 | X9: Other: multi-hit doubles Strength bonus | Y9: =ROUND((I9*Rules!$B$28+J9*Rules!$B$28*Rules!$B$24+K9*Rules!$B$29+L9*Rules!$B$30+M9*Rules!$B$31+N9*Rules!$B$32+(O9*Rules!$B$33+P9*Rules!$B$34+Q9*Rules!$B$35)*IF(R9="Y",Rules!$B$24,1)+S9*Rules!$B$36-T9*Rules!$B$37+IF(V9="Y",Rules!$B$38,0)+W9)*IF(C9="Power",Rules!$B$23,1),2) -> 9 | Z9: =ROUND((D9*Rules!$B$16+Rules!$B$17+IF(E9="Legendary",Rules!$B$21,IF(E9="Rare",Rules!$B$20,IF(E9="Uncommon",Rules!$B$19,Rules!$B$18))))*IF(U9="Y",Rules!$B$22,1),2) -> 9 | AA9: =Y9-Z9 -> 0 | AB9: =IF(E9="Starter",IF(AA9<0,"Starter (under on purpose)","Starter too strong"),IF(ABS(AA9)<=Rules!$B$25,"Balanced",IF(AA9>0,"Over budget","Under budget"))) -> Balanced
A10: C06 | B10: Poisoned Blade | C10: Attack | D10: 1 | E10: Common | F10: Venom | G10: Deal 3 damage. Apply 4 Poison. | H10: Deal 4 damage. Apply 6 Poison. | I10: 3 | Q10: 4 | Y10: =ROUND((I10*Rules!$B$28+J10*Rules!$B$28*Rules!$B$24+K10*Rules!$B$29+L10*Rules!$B$30+M10*Rules!$B$31+N10*Rules!$B$32+(O10*Rules!$B$33+P10*Rules!$B$34+Q10*Rules!$B$35)*IF(R10="Y",Rules!$B$24,1)+S10*Rules!$B$36-T10*Rules!$B$37+IF(V10="Y",Rules!$B$38,0)+W10)*IF(C10="Power",Rules!$B$23,1),2) -> 9 | Z10: =ROUND((D10*Rules!$B$16+Rules!$B$17+IF(E10="Legendary",Rules!$B$21,IF(E10="Rare",Rules!$B$20,IF(E10="Uncommon",Rules!$B$19,Rules!$B$18))))*IF(U10="Y",Rules!$B$22,1),2) -> 9 | AA10: =Y10-Z10 -> 0 | AB10: =IF(E10="Starter",IF(AA10<0,"Starter (under on purpose)","Starter too strong"),IF(ABS(AA10)<=Rules!$B$25,"Balanced",IF(AA10>0,"Over budget","Under budget"))) -> Balanced
A11: C07 | B11: Shield Slam | C11: Attack | D11: 1 | E11: Common | F11: Guardian | G11: Deal 4 damage. Gain 4 block. | H11: Deal 6 damage. Gain 6 block. | I11: 4 | K11: 4 | Y11: =ROUND((I11*Rules!$B$28+J11*Rules!$B$28*Rules!$B$24+K11*Rules!$B$29+L11*Rules!$B$30+M11*Rules!$B$31+N11*Rules!$B$32+(O11*Rules!$B$33+P11*Rules!$B$34+Q11*Rules!$B$35)*IF(R11="Y",Rules!$B$24,1)+S11*Rules!$B$36-T11*Rules!$B$37+IF(V11="Y",Rules!$B$38,0)+W11)*IF(C11="Power",Rules!$B$23,1),2) -> 8.8 | Z11: =ROUND((D11*Rules!$B$16+Rules!$B$17+IF(E11="Legendary",Rules!$B$21,IF(E11="Rare",Rules!$B$20,IF(E11="Uncommon",Rules!$B$19,Rules!$B$18))))*IF(U11="Y",Rules!$B$22,1),2) -> 9 | AA11: =Y11-Z11 -> -0.2 | AB11: =IF(E11="Starter",IF(AA11<0,"Starter (under on purpose)","Starter too strong"),IF(ABS(AA11)<=Rules!$B$25,"Balanced",IF(AA11>0,"Over budget","Under budget"))) -> Balanced
A12: C08 | B12: Venom Fang | C12: Skill | D12: 0 | E12: Common | F12: Venom | G12: Apply 2 Poison. | H12: Apply 3 Poison. | Q12: 2 | Y12: =ROUND((I12*Rules!$B$28+J12*Rules!$B$28*Rules!$B$24+K12*Rules!$B$29+L12*Rules!$B$30+M12*Rules!$B$31+N12*Rules!$B$32+(O12*Rules!$B$33+P12*Rules!$B$34+Q12*Rules!$B$35)*IF(R12="Y",Rules!$B$24,1)+S12*Rules!$B$36-T12*Rules!$B$37+IF(V12="Y",Rules!$B$38,0)+W12)*IF(C12="Power",Rules!$B$23,1),2) -> 3 | Z12: =ROUND((D12*Rules!$B$16+Rules!$B$17+IF(E12="Legendary",Rules!$B$21,IF(E12="Rare",Rules!$B$20,IF(E12="Uncommon",Rules!$B$19,Rules!$B$18))))*IF(U12="Y",Rules!$B$22,1),2) -> 3 | AA12: =Y12-Z12 -> 0 | AB12: =IF(E12="Starter",IF(AA12<0,"Starter (under on purpose)","Starter too strong"),IF(ABS(AA12)<=Rules!$B$25,"Balanced",IF(AA12>0,"Over budget","Under budget"))) -> Balanced
A13: C09 | B13: Pommel Strike | C13: Attack | D13: 1 | E13: Common | F13: Tactician | G13: Deal 5 damage. Draw 1 card. | H13: Deal 7 damage. Draw 1 card. | I13: 5 | M13: 1 | Y13: =ROUND((I13*Rules!$B$28+J13*Rules!$B$28*Rules!$B$24+K13*Rules!$B$29+L13*Rules!$B$30+M13*Rules!$B$31+N13*Rules!$B$32+(O13*Rules!$B$33+P13*Rules!$B$34+Q13*Rules!$B$35)*IF(R13="Y",Rules!$B$24,1)+S13*Rules!$B$36-T13*Rules!$B$37+IF(V13="Y",Rules!$B$38,0)+W13)*IF(C13="Power",Rules!$B$23,1),2) -> 9 | Z13: =ROUND((D13*Rules!$B$16+Rules!$B$17+IF(E13="Legendary",Rules!$B$21,IF(E13="Rare",Rules!$B$20,IF(E13="Uncommon",Rules!$B$19,Rules!$B$18))))*IF(U13="Y",Rules!$B$22,1),2) -> 9 | AA13: =Y13-Z13 -> 0 | AB13: =IF(E13="Starter",IF(AA13<0,"Starter (under on purpose)","Starter too strong"),IF(ABS(AA13)<=Rules!$B$25,"Balanced",IF(AA13>0,"Over budget","Under budget"))) -> Balanced
A14: C10 | B14: Torch Swing | C14: Attack | D14: 1 | E14: Common | F14: Tactician | G14: Deal 6 damage. Apply 1 Vulnerable. | H14: Deal 8 damage. Apply 2 Vulnerable. | I14: 6 | P14: 1 | Y14: =ROUND((I14*Rules!$B$28+J14*Rules!$B$28*Rules!$B$24+K14*Rules!$B$29+L14*Rules!$B$30+M14*Rules!$B$31+N14*Rules!$B$32+(O14*Rules!$B$33+P14*Rules!$B$34+Q14*Rules!$B$35)*IF(R14="Y",Rules!$B$24,1)+S14*Rules!$B$36-T14*Rules!$B$37+IF(V14="Y",Rules!$B$38,0)+W14)*IF(C14="Power",Rules!$B$23,1),2) -> 9 | Z14: =ROUND((D14*Rules!$B$16+Rules!$B$17+IF(E14="Legendary",Rules!$B$21,IF(E14="Rare",Rules!$B$20,IF(E14="Uncommon",Rules!$B$19,Rules!$B$18))))*IF(U14="Y",Rules!$B$22,1),2) -> 9 | AA14: =Y14-Z14 -> 0 | AB14: =IF(E14="Starter",IF(AA14<0,"Starter (under on purpose)","Starter too strong"),IF(ABS(AA14)<=Rules!$B$25,"Balanced",IF(AA14>0,"Over budget","Under budget"))) -> Balanced
A15: C11 | B15: Brace | C15: Skill | D15: 1 | E15: Common | F15: Guardian | G15: Gain 7 block. | H15: Gain 10 block. | K15: 7 | Y15: =ROUND((I15*Rules!$B$28+J15*Rules!$B$28*Rules!$B$24+K15*Rules!$B$29+L15*Rules!$B$30+M15*Rules!$B$31+N15*Rules!$B$32+(O15*Rules!$B$33+P15*Rules!$B$34+Q15*Rules!$B$35)*IF(R15="Y",Rules!$B$24,1)+S15*Rules!$B$36-T15*Rules!$B$37+IF(V15="Y",Rules!$B$38,0)+W15)*IF(C15="Power",Rules!$B$23,1),2) -> 8.4 | Z15: =ROUND((D15*Rules!$B$16+Rules!$B$17+IF(E15="Legendary",Rules!$B$21,IF(E15="Rare",Rules!$B$20,IF(E15="Uncommon",Rules!$B$19,Rules!$B$18))))*IF(U15="Y",Rules!$B$22,1),2) -> 9 | AA15: =Y15-Z15 -> -0.6 | AB15: =IF(E15="Starter",IF(AA15<0,"Starter (under on purpose)","Starter too strong"),IF(ABS(AA15)<=Rules!$B$25,"Balanced",IF(AA15>0,"Over budget","Under budget"))) -> Balanced
A16: C12 | B16: Raise Shield | C16: Skill | D16: 2 | E16: Common | F16: Guardian | G16: Gain 12 block. | H16: Gain 16 block. | K16: 12 | Y16: =ROUND((I16*Rules!$B$28+J16*Rules!$B$28*Rules!$B$24+K16*Rules!$B$29+L16*Rules!$B$30+M16*Rules!$B$31+N16*Rules!$B$32+(O16*Rules!$B$33+P16*Rules!$B$34+Q16*Rules!$B$35)*IF(R16="Y",Rules!$B$24,1)+S16*Rules!$B$36-T16*Rules!$B$37+IF(V16="Y",Rules!$B$38,0)+W16)*IF(C16="Power",Rules!$B$23,1),2) -> 14.4 | Z16: =ROUND((D16*Rules!$B$16+Rules!$B$17+IF(E16="Legendary",Rules!$B$21,IF(E16="Rare",Rules!$B$20,IF(E16="Uncommon",Rules!$B$19,Rules!$B$18))))*IF(U16="Y",Rules!$B$22,1),2) -> 15 | AA16: =Y16-Z16 -> -0.6 | AB16: =IF(E16="Starter",IF(AA16<0,"Starter (under on purpose)","Starter too strong"),IF(ABS(AA16)<=Rules!$B$25,"Balanced",IF(AA16>0,"Over budget","Under budget"))) -> Balanced
A17: C13 | B17: Dodge Roll | C17: Skill | D17: 1 | E17: Common | F17: Guardian | G17: Gain 4 block. Draw 1 card. | H17: Gain 6 block. Draw 1 card. | K17: 4 | M17: 1 | Y17: =ROUND((I17*Rules!$B$28+J17*Rules!$B$28*Rules!$B$24+K17*Rules!$B$29+L17*Rules!$B$30+M17*Rules!$B$31+N17*Rules!$B$32+(O17*Rules!$B$33+P17*Rules!$B$34+Q17*Rules!$B$35)*IF(R17="Y",Rules!$B$24,1)+S17*Rules!$B$36-T17*Rules!$B$37+IF(V17="Y",Rules!$B$38,0)+W17)*IF(C17="Power",Rules!$B$23,1),2) -> 8.8 | Z17: =ROUND((D17*Rules!$B$16+Rules!$B$17+IF(E17="Legendary",Rules!$B$21,IF(E17="Rare",Rules!$B$20,IF(E17="Uncommon",Rules!$B$19,Rules!$B$18))))*IF(U17="Y",Rules!$B$22,1),2) -> 9 | AA17: =Y17-Z17 -> -0.2 | AB17: =IF(E17="Starter",IF(AA17<0,"Starter (under on purpose)","Starter too strong"),IF(ABS(AA17)<=Rules!$B$25,"Balanced",IF(AA17>0,"Over budget","Under budget"))) -> Balanced
A18: C14 | B18: Toxic Vial | C18: Skill | D18: 1 | E18: Common | F18: Venom | G18: Apply 6 Poison. | H18: Apply 9 Poison. | Q18: 6 | Y18: =ROUND((I18*Rules!$B$28+J18*Rules!$B$28*Rules!$B$24+K18*Rules!$B$29+L18*Rules!$B$30+M18*Rules!$B$31+N18*Rules!$B$32+(O18*Rules!$B$33+P18*Rules!$B$34+Q18*Rules!$B$35)*IF(R18="Y",Rules!$B$24,1)+S18*Rules!$B$36-T18*Rules!$B$37+IF(V18="Y",Rules!$B$38,0)+W18)*IF(C18="Power",Rules!$B$23,1),2) -> 9 | Z18: =ROUND((D18*Rules!$B$16+Rules!$B$17+IF(E18="Legendary",Rules!$B$21,IF(E18="Rare",Rules!$B$20,IF(E18="Uncommon",Rules!$B$19,Rules!$B$18))))*IF(U18="Y",Rules!$B$22,1),2) -> 9 | AA18: =Y18-Z18 -> 0 | AB18: =IF(E18="Starter",IF(AA18<0,"Starter (under on purpose)","Starter too strong"),IF(ABS(AA18)<=Rules!$B$25,"Balanced",IF(AA18>0,"Over budget","Under budget"))) -> Balanced
A19: C15 | B19: Bandage | C19: Skill | D19: 1 | E19: Common | F19: Neutral | G19: Gain 4 block. Heal 4 HP. Exhaust. | H19: Gain 5 block. Heal 6 HP. Exhaust. | K19: 4 | L19: 4 | U19: Y | X19: Only in-combat heal at Common | Y19: =ROUND((I19*Rules!$B$28+J19*Rules!$B$28*Rules!$B$24+K19*Rules!$B$29+L19*Rules!$B$30+M19*Rules!$B$31+N19*Rules!$B$32+(O19*Rules!$B$33+P19*Rules!$B$34+Q19*Rules!$B$35)*IF(R19="Y",Rules!$B$24,1)+S19*Rules!$B$36-T19*Rules!$B$37+IF(V19="Y",Rules!$B$38,0)+W19)*IF(C19="Power",Rules!$B$23,1),2) -> 10.8 | Z19: =ROUND((D19*Rules!$B$16+Rules!$B$17+IF(E19="Legendary",Rules!$B$21,IF(E19="Rare",Rules!$B$20,IF(E19="Uncommon",Rules!$B$19,Rules!$B$18))))*IF(U19="Y",Rules!$B$22,1),2) -> 11.7 | AA19: =Y19-Z19 -> -0.9 | AB19: =IF(E19="Starter",IF(AA19<0,"Starter (under on purpose)","Starter too strong"),IF(ABS(AA19)<=Rules!$B$25,"Balanced",IF(AA19>0,"Over budget","Under budget"))) -> Balanced
A20: C16 | B20: Scout Ahead | C20: Skill | D20: 1 | E20: Common | F20: Tactician | G20: Draw 2 cards. | H20: Draw 3 cards. | M20: 2 | Y20: =ROUND((I20*Rules!$B$28+J20*Rules!$B$28*Rules!$B$24+K20*Rules!$B$29+L20*Rules!$B$30+M20*Rules!$B$31+N20*Rules!$B$32+(O20*Rules!$B$33+P20*Rules!$B$34+Q20*Rules!$B$35)*IF(R20="Y",Rules!$B$24,1)+S20*Rules!$B$36-T20*Rules!$B$37+IF(V20="Y",Rules!$B$38,0)+W20)*IF(C20="Power",Rules!$B$23,1),2) -> 8 | Z20: =ROUND((D20*Rules!$B$16+Rules!$B$17+IF(E20="Legendary",Rules!$B$21,IF(E20="Rare",Rules!$B$20,IF(E20="Uncommon",Rules!$B$19,Rules!$B$18))))*IF(U20="Y",Rules!$B$22,1),2) -> 9 | AA20: =Y20-Z20 -> -1 | AB20: =IF(E20="Starter",IF(AA20<0,"Starter (under on purpose)","Starter too strong"),IF(ABS(AA20)<=Rules!$B$25,"Balanced",IF(AA20>0,"Over budget","Under budget"))) -> Balanced
A21: C17 | B21: Smoke Bomb | C21: Skill | D21: 1 | E21: Common | F21: Tactician | G21: Apply 2 Weak to ALL enemies. | H21: Apply 3 Weak to ALL enemies. | O21: 2 | R21: Y | Y21: =ROUND((I21*Rules!$B$28+J21*Rules!$B$28*Rules!$B$24+K21*Rules!$B$29+L21*Rules!$B$30+M21*Rules!$B$31+N21*Rules!$B$32+(O21*Rules!$B$33+P21*Rules!$B$34+Q21*Rules!$B$35)*IF(R21="Y",Rules!$B$24,1)+S21*Rules!$B$36-T21*Rules!$B$37+IF(V21="Y",Rules!$B$38,0)+W21)*IF(C21="Power",Rules!$B$23,1),2) -> 9 | Z21: =ROUND((D21*Rules!$B$16+Rules!$B$17+IF(E21="Legendary",Rules!$B$21,IF(E21="Rare",Rules!$B$20,IF(E21="Uncommon",Rules!$B$19,Rules!$B$18))))*IF(U21="Y",Rules!$B$22,1),2) -> 9 | AA21: =Y21-Z21 -> 0 | AB21: =IF(E21="Starter",IF(AA21<0,"Starter (under on purpose)","Starter too strong"),IF(ABS(AA21)<=Rules!$B$25,"Balanced",IF(AA21>0,"Over budget","Under budget"))) -> Balanced
A22: C18 | B22: Sharpen | C22: Skill | D22: 0 | E22: Common | F22: Brawler | G22: Your next Attack this turn deals 3 extra damage. | H22: Your next Attack this turn deals 5 extra damage. | W22: 3 | X22: Other: conditional +3 damage | Y22: =ROUND((I22*Rules!$B$28+J22*Rules!$B$28*Rules!$B$24+K22*Rules!$B$29+L22*Rules!$B$30+M22*Rules!$B$31+N22*Rules!$B$32+(O22*Rules!$B$33+P22*Rules!$B$34+Q22*Rules!$B$35)*IF(R22="Y",Rules!$B$24,1)+S22*Rules!$B$36-T22*Rules!$B$37+IF(V22="Y",Rules!$B$38,0)+W22)*IF(C22="Power",Rules!$B$23,1),2) -> 3 | Z22: =ROUND((D22*Rules!$B$16+Rules!$B$17+IF(E22="Legendary",Rules!$B$21,IF(E22="Rare",Rules!$B$20,IF(E22="Uncommon",Rules!$B$19,Rules!$B$18))))*IF(U22="Y",Rules!$B$22,1),2) -> 3 | AA22: =Y22-Z22 -> 0 | AB22: =IF(E22="Starter",IF(AA22<0,"Starter (under on purpose)","Starter too strong"),IF(ABS(AA22)<=Rules!$B$25,"Balanced",IF(AA22>0,"Over budget","Under budget"))) -> Balanced
A23: C19 | B23: Deep Breath | C23: Skill | D23: 0 | E23: Common | F23: Tactician | G23: Draw 1 card. Exhaust. | H23: Draw 2 cards. Exhaust. | M23: 1 | U23: Y | Y23: =ROUND((I23*Rules!$B$28+J23*Rules!$B$28*Rules!$B$24+K23*Rules!$B$29+L23*Rules!$B$30+M23*Rules!$B$31+N23*Rules!$B$32+(O23*Rules!$B$33+P23*Rules!$B$34+Q23*Rules!$B$35)*IF(R23="Y",Rules!$B$24,1)+S23*Rules!$B$36-T23*Rules!$B$37+IF(V23="Y",Rules!$B$38,0)+W23)*IF(C23="Power",Rules!$B$23,1),2) -> 4 | Z23: =ROUND((D23*Rules!$B$16+Rules!$B$17+IF(E23="Legendary",Rules!$B$21,IF(E23="Rare",Rules!$B$20,IF(E23="Uncommon",Rules!$B$19,Rules!$B$18))))*IF(U23="Y",Rules!$B$22,1),2) -> 3.9 | AA23: =Y23-Z23 -> 0.1 | AB23: =IF(E23="Starter",IF(AA23<0,"Starter (under on purpose)","Starter too strong"),IF(ABS(AA23)<=Rules!$B$25,"Balanced",IF(AA23>0,"Over budget","Under budget"))) -> Balanced
A24: C20 | B24: Stand Firm | C24: Skill | D24: 1 | E24: Common | F24: Guardian | G24: Gain 5 block. Apply 1 Weak. | H24: Gain 7 block. Apply 1 Weak. | K24: 5 | O24: 1 | Y24: =ROUND((I24*Rules!$B$28+J24*Rules!$B$28*Rules!$B$24+K24*Rules!$B$29+L24*Rules!$B$30+M24*Rules!$B$31+N24*Rules!$B$32+(O24*Rules!$B$33+P24*Rules!$B$34+Q24*Rules!$B$35)*IF(R24="Y",Rules!$B$24,1)+S24*Rules!$B$36-T24*Rules!$B$37+IF(V24="Y",Rules!$B$38,0)+W24)*IF(C24="Power",Rules!$B$23,1),2) -> 9 | Z24: =ROUND((D24*Rules!$B$16+Rules!$B$17+IF(E24="Legendary",Rules!$B$21,IF(E24="Rare",Rules!$B$20,IF(E24="Uncommon",Rules!$B$19,Rules!$B$18))))*IF(U24="Y",Rules!$B$22,1),2) -> 9 | AA24: =Y24-Z24 -> 0 | AB24: =IF(E24="Starter",IF(AA24<0,"Starter (under on purpose)","Starter too strong"),IF(ABS(AA24)<=Rules!$B$25,"Balanced",IF(AA24>0,"Over budget","Under budget"))) -> Balanced
A25: C21 | B25: Rope Swing | C25: Attack | D25: 1 | E25: Common | F25: Neutral | G25: Deal 5 damage. Gain 3 block. | H25: Deal 7 damage. Gain 4 block. | I25: 5 | K25: 3 | Y25: =ROUND((I25*Rules!$B$28+J25*Rules!$B$28*Rules!$B$24+K25*Rules!$B$29+L25*Rules!$B$30+M25*Rules!$B$31+N25*Rules!$B$32+(O25*Rules!$B$33+P25*Rules!$B$34+Q25*Rules!$B$35)*IF(R25="Y",Rules!$B$24,1)+S25*Rules!$B$36-T25*Rules!$B$37+IF(V25="Y",Rules!$B$38,0)+W25)*IF(C25="Power",Rules!$B$23,1),2) -> 8.6 | Z25: =ROUND((D25*Rules!$B$16+Rules!$B$17+IF(E25="Legendary",Rules!$B$21,IF(E25="Rare",Rules!$B$20,IF(E25="Uncommon",Rules!$B$19,Rules!$B$18))))*IF(U25="Y",Rules!$B$22,1),2) -> 9 | AA25: =Y25-Z25 -> -0.4 | AB25: =IF(E25="Starter",IF(AA25<0,"Starter (under on purpose)","Starter too strong"),IF(ABS(AA25)<=Rules!$B$25,"Balanced",IF(AA25>0,"Over budget","Under budget"))) -> Balanced
A26: C22 | B26: Torchlight | C26: Skill | D26: 1 | E26: Common | F26: Neutral | G26: Gain 3 block. Draw 1 card. Retain. | H26: Gain 5 block. Draw 1 card. Retain. | K26: 3 | M26: 1 | V26: Y | Y26: =ROUND((I26*Rules!$B$28+J26*Rules!$B$28*Rules!$B$24+K26*Rules!$B$29+L26*Rules!$B$30+M26*Rules!$B$31+N26*Rules!$B$32+(O26*Rules!$B$33+P26*Rules!$B$34+Q26*Rules!$B$35)*IF(R26="Y",Rules!$B$24,1)+S26*Rules!$B$36-T26*Rules!$B$37+IF(V26="Y",Rules!$B$38,0)+W26)*IF(C26="Power",Rules!$B$23,1),2) -> 9.6 | Z26: =ROUND((D26*Rules!$B$16+Rules!$B$17+IF(E26="Legendary",Rules!$B$21,IF(E26="Rare",Rules!$B$20,IF(E26="Uncommon",Rules!$B$19,Rules!$B$18))))*IF(U26="Y",Rules!$B$22,1),2) -> 9 | AA26: =Y26-Z26 -> 0.6 | AB26: =IF(E26="Starter",IF(AA26<0,"Starter (under on purpose)","Starter too strong"),IF(ABS(AA26)<=Rules!$B$25,"Balanced",IF(AA26>0,"Over budget","Under budget"))) -> Balanced
A27: C23 | B27: Rations | C27: Skill | D27: 1 | E27: Common | F27: Neutral | G27: Heal 5 HP. Draw 1 card. Exhaust. | H27: Heal 7 HP. Draw 1 card. Exhaust. | L27: 5 | M27: 1 | U27: Y | Y27: =ROUND((I27*Rules!$B$28+J27*Rules!$B$28*Rules!$B$24+K27*Rules!$B$29+L27*Rules!$B$30+M27*Rules!$B$31+N27*Rules!$B$32+(O27*Rules!$B$33+P27*Rules!$B$34+Q27*Rules!$B$35)*IF(R27="Y",Rules!$B$24,1)+S27*Rules!$B$36-T27*Rules!$B$37+IF(V27="Y",Rules!$B$38,0)+W27)*IF(C27="Power",Rules!$B$23,1),2) -> 11.5 | Z27: =ROUND((D27*Rules!$B$16+Rules!$B$17+IF(E27="Legendary",Rules!$B$21,IF(E27="Rare",Rules!$B$20,IF(E27="Uncommon",Rules!$B$19,Rules!$B$18))))*IF(U27="Y",Rules!$B$22,1),2) -> 11.7 | AA27: =Y27-Z27 -> -0.2 | AB27: =IF(E27="Starter",IF(AA27<0,"Starter (under on purpose)","Starter too strong"),IF(ABS(AA27)<=Rules!$B$25,"Balanced",IF(AA27>0,"Over budget","Under budget"))) -> Balanced
A28: C24 | B28: Crossbow Bolt | C28: Attack | D28: 2 | E28: Common | F28: Neutral | G28: Deal 12 damage. Apply 1 Weak. | H28: Deal 16 damage. Apply 1 Weak. | I28: 12 | O28: 1 | Y28: =ROUND((I28*Rules!$B$28+J28*Rules!$B$28*Rules!$B$24+K28*Rules!$B$29+L28*Rules!$B$30+M28*Rules!$B$31+N28*Rules!$B$32+(O28*Rules!$B$33+P28*Rules!$B$34+Q28*Rules!$B$35)*IF(R28="Y",Rules!$B$24,1)+S28*Rules!$B$36-T28*Rules!$B$37+IF(V28="Y",Rules!$B$38,0)+W28)*IF(C28="Power",Rules!$B$23,1),2) -> 15 | Z28: =ROUND((D28*Rules!$B$16+Rules!$B$17+IF(E28="Legendary",Rules!$B$21,IF(E28="Rare",Rules!$B$20,IF(E28="Uncommon",Rules!$B$19,Rules!$B$18))))*IF(U28="Y",Rules!$B$22,1),2) -> 15 | AA28: =Y28-Z28 -> 0 | AB28: =IF(E28="Starter",IF(AA28<0,"Starter (under on purpose)","Starter too strong"),IF(ABS(AA28)<=Rules!$B$25,"Balanced",IF(AA28>0,"Over budget","Under budget"))) -> Balanced
A29: C25 | B29: Warm Up | C29: Attack | D29: 1 | E29: Common | F29: Brawler | G29: Deal 5 damage. Gain 1 Strength. | H29: Deal 7 damage. Gain 1 Strength. | I29: 5 | S29: 1 | Y29: =ROUND((I29*Rules!$B$28+J29*Rules!$B$28*Rules!$B$24+K29*Rules!$B$29+L29*Rules!$B$30+M29*Rules!$B$31+N29*Rules!$B$32+(O29*Rules!$B$33+P29*Rules!$B$34+Q29*Rules!$B$35)*IF(R29="Y",Rules!$B$24,1)+S29*Rules!$B$36-T29*Rules!$B$37+IF(V29="Y",Rules!$B$38,0)+W29)*IF(C29="Power",Rules!$B$23,1),2) -> 9 | Z29: =ROUND((D29*Rules!$B$16+Rules!$B$17+IF(E29="Legendary",Rules!$B$21,IF(E29="Rare",Rules!$B$20,IF(E29="Uncommon",Rules!$B$19,Rules!$B$18))))*IF(U29="Y",Rules!$B$22,1),2) -> 9 | AA29: =Y29-Z29 -> 0 | AB29: =IF(E29="Starter",IF(AA29<0,"Starter (under on purpose)","Starter too strong"),IF(ABS(AA29)<=Rules!$B$25,"Balanced",IF(AA29>0,"Over budget","Under budget"))) -> Balanced
A30: C26 | B30: Uppercut | C30: Attack | D30: 1 | E30: Common | F30: Brawler | G30: Deal 6 damage. Apply 1 Weak. | H30: Deal 8 damage. Apply 2 Weak. | I30: 6 | O30: 1 | Y30: =ROUND((I30*Rules!$B$28+J30*Rules!$B$28*Rules!$B$24+K30*Rules!$B$29+L30*Rules!$B$30+M30*Rules!$B$31+N30*Rules!$B$32+(O30*Rules!$B$33+P30*Rules!$B$34+Q30*Rules!$B$35)*IF(R30="Y",Rules!$B$24,1)+S30*Rules!$B$36-T30*Rules!$B$37+IF(V30="Y",Rules!$B$38,0)+W30)*IF(C30="Power",Rules!$B$23,1),2) -> 9 | Z30: =ROUND((D30*Rules!$B$16+Rules!$B$17+IF(E30="Legendary",Rules!$B$21,IF(E30="Rare",Rules!$B$20,IF(E30="Uncommon",Rules!$B$19,Rules!$B$18))))*IF(U30="Y",Rules!$B$22,1),2) -> 9 | AA30: =Y30-Z30 -> 0 | AB30: =IF(E30="Starter",IF(AA30<0,"Starter (under on purpose)","Starter too strong"),IF(ABS(AA30)<=Rules!$B$25,"Balanced",IF(AA30>0,"Over budget","Under budget"))) -> Balanced
A31: C27 | B31: Flurry | C31: Attack | D31: 1 | E31: Common | F31: Brawler | G31: Deal 2 damage 4 times. | H31: Deal 3 damage 4 times. | I31: 8 | W31: 1 | X31: Other: 4 hits quadruple Strength bonus | Y31: =ROUND((I31*Rules!$B$28+J31*Rules!$B$28*Rules!$B$24+K31*Rules!$B$29+L31*Rules!$B$30+M31*Rules!$B$31+N31*Rules!$B$32+(O31*Rules!$B$33+P31*Rules!$B$34+Q31*Rules!$B$35)*IF(R31="Y",Rules!$B$24,1)+S31*Rules!$B$36-T31*Rules!$B$37+IF(V31="Y",Rules!$B$38,0)+W31)*IF(C31="Power",Rules!$B$23,1),2) -> 9 | Z31: =ROUND((D31*Rules!$B$16+Rules!$B$17+IF(E31="Legendary",Rules!$B$21,IF(E31="Rare",Rules!$B$20,IF(E31="Uncommon",Rules!$B$19,Rules!$B$18))))*IF(U31="Y",Rules!$B$22,1),2) -> 9 | AA31: =Y31-Z31 -> 0 | AB31: =IF(E31="Starter",IF(AA31<0,"Starter (under on purpose)","Starter too strong"),IF(ABS(AA31)<=Rules!$B$25,"Balanced",IF(AA31>0,"Over budget","Under budget"))) -> Balanced
A32: C28 | B32: Double Tap | C32: Attack | D32: 0 | E32: Common | F32: Brawler | G32: Deal 2 damage twice. | H32: Deal 3 damage twice. | I32: 4 | X32: Multi-hit; pairs with Strength | Y32: =ROUND((I32*Rules!$B$28+J32*Rules!$B$28*Rules!$B$24+K32*Rules!$B$29+L32*Rules!$B$30+M32*Rules!$B$31+N32*Rules!$B$32+(O32*Rules!$B$33+P32*Rules!$B$34+Q32*Rules!$B$35)*IF(R32="Y",Rules!$B$24,1)+S32*Rules!$B$36-T32*Rules!$B$37+IF(V32="Y",Rules!$B$38,0)+W32)*IF(C32="Power",Rules!$B$23,1),2) -> 4 | Z32: =ROUND((D32*Rules!$B$16+Rules!$B$17+IF(E32="Legendary",Rules!$B$21,IF(E32="Rare",Rules!$B$20,IF(E32="Uncommon",Rules!$B$19,Rules!$B$18))))*IF(U32="Y",Rules!$B$22,1),2) -> 3 | AA32: =Y32-Z32 -> 1 | AB32: =IF(E32="Starter",IF(AA32<0,"Starter (under on purpose)","Starter too strong"),IF(ABS(AA32)<=Rules!$B$25,"Balanced",IF(AA32>0,"Over budget","Under budget"))) -> Balanced
A33: C29 | B33: Charge | C33: Attack | D33: 2 | E33: Common | F33: Brawler | G33: Deal 10 damage. Gain 1 Strength. | H33: Deal 13 damage. Gain 1 Strength. | I33: 10 | S33: 1 | Y33: =ROUND((I33*Rules!$B$28+J33*Rules!$B$28*Rules!$B$24+K33*Rules!$B$29+L33*Rules!$B$30+M33*Rules!$B$31+N33*Rules!$B$32+(O33*Rules!$B$33+P33*Rules!$B$34+Q33*Rules!$B$35)*IF(R33="Y",Rules!$B$24,1)+S33*Rules!$B$36-T33*Rules!$B$37+IF(V33="Y",Rules!$B$38,0)+W33)*IF(C33="Power",Rules!$B$23,1),2) -> 14 | Z33: =ROUND((D33*Rules!$B$16+Rules!$B$17+IF(E33="Legendary",Rules!$B$21,IF(E33="Rare",Rules!$B$20,IF(E33="Uncommon",Rules!$B$19,Rules!$B$18))))*IF(U33="Y",Rules!$B$22,1),2) -> 15 | AA33: =Y33-Z33 -> -1 | AB33: =IF(E33="Starter",IF(AA33<0,"Starter (under on purpose)","Starter too strong"),IF(ABS(AA33)<=Rules!$B$25,"Balanced",IF(AA33>0,"Over budget","Under budget"))) -> Balanced
A34: C30 | B34: Rage Fist | C34: Attack | D34: 1 | E34: Common | F34: Brawler | G34: Deal 10 damage. Lose 1 HP. | H34: Deal 13 damage. Lose 1 HP. | I34: 10 | T34: 1 | Y34: =ROUND((I34*Rules!$B$28+J34*Rules!$B$28*Rules!$B$24+K34*Rules!$B$29+L34*Rules!$B$30+M34*Rules!$B$31+N34*Rules!$B$32+(O34*Rules!$B$33+P34*Rules!$B$34+Q34*Rules!$B$35)*IF(R34="Y",Rules!$B$24,1)+S34*Rules!$B$36-T34*Rules!$B$37+IF(V34="Y",Rules!$B$38,0)+W34)*IF(C34="Power",Rules!$B$23,1),2) -> 8.5 | Z34: =ROUND((D34*Rules!$B$16+Rules!$B$17+IF(E34="Legendary",Rules!$B$21,IF(E34="Rare",Rules!$B$20,IF(E34="Uncommon",Rules!$B$19,Rules!$B$18))))*IF(U34="Y",Rules!$B$22,1),2) -> 9 | AA34: =Y34-Z34 -> -0.5 | AB34: =IF(E34="Starter",IF(AA34<0,"Starter (under on purpose)","Starter too strong"),IF(ABS(AA34)<=Rules!$B$25,"Balanced",IF(AA34>0,"Over budget","Under budget"))) -> Balanced
A35: C31 | B35: Grit Teeth | C35: Skill | D35: 1 | E35: Common | F35: Brawler | G35: Gain 4 block. Gain 1 Strength. | H35: Gain 6 block. Gain 1 Strength. | K35: 4 | S35: 1 | Y35: =ROUND((I35*Rules!$B$28+J35*Rules!$B$28*Rules!$B$24+K35*Rules!$B$29+L35*Rules!$B$30+M35*Rules!$B$31+N35*Rules!$B$32+(O35*Rules!$B$33+P35*Rules!$B$34+Q35*Rules!$B$35)*IF(R35="Y",Rules!$B$24,1)+S35*Rules!$B$36-T35*Rules!$B$37+IF(V35="Y",Rules!$B$38,0)+W35)*IF(C35="Power",Rules!$B$23,1),2) -> 8.8 | Z35: =ROUND((D35*Rules!$B$16+Rules!$B$17+IF(E35="Legendary",Rules!$B$21,IF(E35="Rare",Rules!$B$20,IF(E35="Uncommon",Rules!$B$19,Rules!$B$18))))*IF(U35="Y",Rules!$B$22,1),2) -> 9 | AA35: =Y35-Z35 -> -0.2 | AB35: =IF(E35="Starter",IF(AA35<0,"Starter (under on purpose)","Starter too strong"),IF(ABS(AA35)<=Rules!$B$25,"Balanced",IF(AA35>0,"Over budget","Under budget"))) -> Balanced
A36: C32 | B36: Wild Swing | C36: Attack | D36: 1 | E36: Common | F36: Brawler | G36: Deal 12 damage to a random enemy. | H36: Deal 16 damage to a random enemy. | I36: 12 | W36: -3 | X36: Other: random target is a drawback | Y36: =ROUND((I36*Rules!$B$28+J36*Rules!$B$28*Rules!$B$24+K36*Rules!$B$29+L36*Rules!$B$30+M36*Rules!$B$31+N36*Rules!$B$32+(O36*Rules!$B$33+P36*Rules!$B$34+Q36*Rules!$B$35)*IF(R36="Y",Rules!$B$24,1)+S36*Rules!$B$36-T36*Rules!$B$37+IF(V36="Y",Rules!$B$38,0)+W36)*IF(C36="Power",Rules!$B$23,1),2) -> 9 | Z36: =ROUND((D36*Rules!$B$16+Rules!$B$17+IF(E36="Legendary",Rules!$B$21,IF(E36="Rare",Rules!$B$20,IF(E36="Uncommon",Rules!$B$19,Rules!$B$18))))*IF(U36="Y",Rules!$B$22,1),2) -> 9 | AA36: =Y36-Z36 -> 0 | AB36: =IF(E36="Starter",IF(AA36<0,"Starter (under on purpose)","Starter too strong"),IF(ABS(AA36)<=Rules!$B$25,"Balanced",IF(AA36>0,"Over budget","Under budget"))) -> Balanced
A37: C33 | B37: Hunker Down | C37: Skill | D37: 1 | E37: Common | F37: Guardian | G37: Gain 6 block. Retain. | H37: Gain 8 block. Retain. | K37: 6 | V37: Y | Y37: =ROUND((I37*Rules!$B$28+J37*Rules!$B$28*Rules!$B$24+K37*Rules!$B$29+L37*Rules!$B$30+M37*Rules!$B$31+N37*Rules!$B$32+(O37*Rules!$B$33+P37*Rules!$B$34+Q37*Rules!$B$35)*IF(R37="Y",Rules!$B$24,1)+S37*Rules!$B$36-T37*Rules!$B$37+IF(V37="Y",Rules!$B$38,0)+W37)*IF(C37="Power",Rules!$B$23,1),2) -> 9.2 | Z37: =ROUND((D37*Rules!$B$16+Rules!$B$17+IF(E37="Legendary",Rules!$B$21,IF(E37="Rare",Rules!$B$20,IF(E37="Uncommon",Rules!$B$19,Rules!$B$18))))*IF(U37="Y",Rules!$B$22,1),2) -> 9 | AA37: =Y37-Z37 -> 0.2 | AB37: =IF(E37="Starter",IF(AA37<0,"Starter (under on purpose)","Starter too strong"),IF(ABS(AA37)<=Rules!$B$25,"Balanced",IF(AA37>0,"Over budget","Under budget"))) -> Balanced
A38: C34 | B38: Buckler Bash | C38: Attack | D38: 1 | E38: Common | F38: Guardian | G38: Deal damage equal to your block. | H38: Costs 0. Deal damage equal to your block. | W38: 8 | X38: NEW: damage_equals_block. PLAYTEST: value ~ typical block (8) | Y38: =ROUND((I38*Rules!$B$28+J38*Rules!$B$28*Rules!$B$24+K38*Rules!$B$29+L38*Rules!$B$30+M38*Rules!$B$31+N38*Rules!$B$32+(O38*Rules!$B$33+P38*Rules!$B$34+Q38*Rules!$B$35)*IF(R38="Y",Rules!$B$24,1)+S38*Rules!$B$36-T38*Rules!$B$37+IF(V38="Y",Rules!$B$38,0)+W38)*IF(C38="Power",Rules!$B$23,1),2) -> 8 | Z38: =ROUND((D38*Rules!$B$16+Rules!$B$17+IF(E38="Legendary",Rules!$B$21,IF(E38="Rare",Rules!$B$20,IF(E38="Uncommon",Rules!$B$19,Rules!$B$18))))*IF(U38="Y",Rules!$B$22,1),2) -> 9 | AA38: =Y38-Z38 -> -1 | AB38: =IF(E38="Starter",IF(AA38<0,"Starter (under on purpose)","Starter too strong"),IF(ABS(AA38)<=Rules!$B$25,"Balanced",IF(AA38>0,"Over budget","Under budget"))) -> Balanced
A39: C35 | B39: Shield Wall | C39: Skill | D39: 2 | E39: Common | F39: Guardian | G39: Gain 9 block. Apply 1 Weak to ALL enemies. | H39: Gain 12 block. Apply 1 Weak to ALL enemies. | K39: 9 | O39: 1 | R39: Y | Y39: =ROUND((I39*Rules!$B$28+J39*Rules!$B$28*Rules!$B$24+K39*Rules!$B$29+L39*Rules!$B$30+M39*Rules!$B$31+N39*Rules!$B$32+(O39*Rules!$B$33+P39*Rules!$B$34+Q39*Rules!$B$35)*IF(R39="Y",Rules!$B$24,1)+S39*Rules!$B$36-T39*Rules!$B$37+IF(V39="Y",Rules!$B$38,0)+W39)*IF(C39="Power",Rules!$B$23,1),2) -> 15.3 | Z39: =ROUND((D39*Rules!$B$16+Rules!$B$17+IF(E39="Legendary",Rules!$B$21,IF(E39="Rare",Rules!$B$20,IF(E39="Uncommon",Rules!$B$19,Rules!$B$18))))*IF(U39="Y",Rules!$B$22,1),2) -> 15 | AA39: =Y39-Z39 -> 0.3 | AB39: =IF(E39="Starter",IF(AA39<0,"Starter (under on purpose)","Starter too strong"),IF(ABS(AA39)<=Rules!$B$25,"Balanced",IF(AA39>0,"Over budget","Under budget"))) -> Balanced
A40: C36 | B40: Fortify | C40: Skill | D40: 0 | E40: Common | F40: Guardian | G40: Gain 3 block. | H40: Gain 5 block. | K40: 3 | Y40: =ROUND((I40*Rules!$B$28+J40*Rules!$B$28*Rules!$B$24+K40*Rules!$B$29+L40*Rules!$B$30+M40*Rules!$B$31+N40*Rules!$B$32+(O40*Rules!$B$33+P40*Rules!$B$34+Q40*Rules!$B$35)*IF(R40="Y",Rules!$B$24,1)+S40*Rules!$B$36-T40*Rules!$B$37+IF(V40="Y",Rules!$B$38,0)+W40)*IF(C40="Power",Rules!$B$23,1),2) -> 3.6 | Z40: =ROUND((D40*Rules!$B$16+Rules!$B$17+IF(E40="Legendary",Rules!$B$21,IF(E40="Rare",Rules!$B$20,IF(E40="Uncommon",Rules!$B$19,Rules!$B$18))))*IF(U40="Y",Rules!$B$22,1),2) -> 3 | AA40: =Y40-Z40 -> 0.6 | AB40: =IF(E40="Starter",IF(AA40<0,"Starter (under on purpose)","Starter too strong"),IF(ABS(AA40)<=Rules!$B$25,"Balanced",IF(AA40>0,"Over budget","Under budget"))) -> Balanced
A41: C37 | B41: Spiked Shield | C41: Attack | D41: 1 | E41: Common | F41: Guardian | G41: Deal 3 damage. Gain 5 block. | H41: Deal 5 damage. Gain 7 block. | I41: 3 | K41: 5 | Y41: =ROUND((I41*Rules!$B$28+J41*Rules!$B$28*Rules!$B$24+K41*Rules!$B$29+L41*Rules!$B$30+M41*Rules!$B$31+N41*Rules!$B$32+(O41*Rules!$B$33+P41*Rules!$B$34+Q41*Rules!$B$35)*IF(R41="Y",Rules!$B$24,1)+S41*Rules!$B$36-T41*Rules!$B$37+IF(V41="Y",Rules!$B$38,0)+W41)*IF(C41="Power",Rules!$B$23,1),2) -> 9 | Z41: =ROUND((D41*Rules!$B$16+Rules!$B$17+IF(E41="Legendary",Rules!$B$21,IF(E41="Rare",Rules!$B$20,IF(E41="Uncommon",Rules!$B$19,Rules!$B$18))))*IF(U41="Y",Rules!$B$22,1),2) -> 9 | AA41: =Y41-Z41 -> 0 | AB41: =IF(E41="Starter",IF(AA41<0,"Starter (under on purpose)","Starter too strong"),IF(ABS(AA41)<=Rules!$B$25,"Balanced",IF(AA41>0,"Over budget","Under budget"))) -> Balanced
A42: C38 | B42: Steadfast | C42: Skill | D42: 1 | E42: Common | F42: Guardian | G42: Gain 5 block. Next turn, gain 3 block. | H42: Gain 7 block. Next turn, gain 4 block. | K42: 8 | X42: Block column = 5 now + 3 next turn | Y42: =ROUND((I42*Rules!$B$28+J42*Rules!$B$28*Rules!$B$24+K42*Rules!$B$29+L42*Rules!$B$30+M42*Rules!$B$31+N42*Rules!$B$32+(O42*Rules!$B$33+P42*Rules!$B$34+Q42*Rules!$B$35)*IF(R42="Y",Rules!$B$24,1)+S42*Rules!$B$36-T42*Rules!$B$37+IF(V42="Y",Rules!$B$38,0)+W42)*IF(C42="Power",Rules!$B$23,1),2) -> 9.6 | Z42: =ROUND((D42*Rules!$B$16+Rules!$B$17+IF(E42="Legendary",Rules!$B$21,IF(E42="Rare",Rules!$B$20,IF(E42="Uncommon",Rules!$B$19,Rules!$B$18))))*IF(U42="Y",Rules!$B$22,1),2) -> 9 | AA42: =Y42-Z42 -> 0.6 | AB42: =IF(E42="Starter",IF(AA42<0,"Starter (under on purpose)","Starter too strong"),IF(ABS(AA42)<=Rules!$B$25,"Balanced",IF(AA42>0,"Over budget","Under budget"))) -> Balanced
A43: C39 | B43: Rebuke | C43: Skill | D43: 1 | E43: Common | F43: Guardian | G43: Gain 4 block. If the enemy intends to attack, apply 2 Weak. | H43: Gain 6 block. If the enemy intends to attack, apply 2 Weak. | K43: 4 | W43: 4 | X43: NEW: if_intent on a status. Other: conditional 2 Weak (~4) | Y43: =ROUND((I43*Rules!$B$28+J43*Rules!$B$28*Rules!$B$24+K43*Rules!$B$29+L43*Rules!$B$30+M43*Rules!$B$31+N43*Rules!$B$32+(O43*Rules!$B$33+P43*Rules!$B$34+Q43*Rules!$B$35)*IF(R43="Y",Rules!$B$24,1)+S43*Rules!$B$36-T43*Rules!$B$37+IF(V43="Y",Rules!$B$38,0)+W43)*IF(C43="Power",Rules!$B$23,1),2) -> 8.8 | Z43: =ROUND((D43*Rules!$B$16+Rules!$B$17+IF(E43="Legendary",Rules!$B$21,IF(E43="Rare",Rules!$B$20,IF(E43="Uncommon",Rules!$B$19,Rules!$B$18))))*IF(U43="Y",Rules!$B$22,1),2) -> 9 | AA43: =Y43-Z43 -> -0.2 | AB43: =IF(E43="Starter",IF(AA43<0,"Starter (under on purpose)","Starter too strong"),IF(ABS(AA43)<=Rules!$B$25,"Balanced",IF(AA43>0,"Over budget","Under budget"))) -> Balanced
A44: C40 | B44: Intercept | C44: Skill | D44: 0 | E44: Common | F44: Guardian | G44: Gain 4 block. Exhaust. | H44: Gain 6 block. Exhaust. | K44: 4 | U44: Y | Y44: =ROUND((I44*Rules!$B$28+J44*Rules!$B$28*Rules!$B$24+K44*Rules!$B$29+L44*Rules!$B$30+M44*Rules!$B$31+N44*Rules!$B$32+(O44*Rules!$B$33+P44*Rules!$B$34+Q44*Rules!$B$35)*IF(R44="Y",Rules!$B$24,1)+S44*Rules!$B$36-T44*Rules!$B$37+IF(V44="Y",Rules!$B$38,0)+W44)*IF(C44="Power",Rules!$B$23,1),2) -> 4.8 | Z44: =ROUND((D44*Rules!$B$16+Rules!$B$17+IF(E44="Legendary",Rules!$B$21,IF(E44="Rare",Rules!$B$20,IF(E44="Uncommon",Rules!$B$19,Rules!$B$18))))*IF(U44="Y",Rules!$B$22,1),2) -> 3.9 | AA44: =Y44-Z44 -> 0.9 | AB44: =IF(E44="Starter",IF(AA44<0,"Starter (under on purpose)","Starter too strong"),IF(ABS(AA44)<=Rules!$B$25,"Balanced",IF(AA44>0,"Over budget","Under budget"))) -> Balanced
A45: C41 | B45: Spit Venom | C45: Skill | D45: 1 | E45: Common | F45: Venom | G45: Apply 4 Poison to ALL enemies. | H45: Apply 6 Poison to ALL enemies. | Q45: 4 | R45: Y | Y45: =ROUND((I45*Rules!$B$28+J45*Rules!$B$28*Rules!$B$24+K45*Rules!$B$29+L45*Rules!$B$30+M45*Rules!$B$31+N45*Rules!$B$32+(O45*Rules!$B$33+P45*Rules!$B$34+Q45*Rules!$B$35)*IF(R45="Y",Rules!$B$24,1)+S45*Rules!$B$36-T45*Rules!$B$37+IF(V45="Y",Rules!$B$38,0)+W45)*IF(C45="Power",Rules!$B$23,1),2) -> 9 | Z45: =ROUND((D45*Rules!$B$16+Rules!$B$17+IF(E45="Legendary",Rules!$B$21,IF(E45="Rare",Rules!$B$20,IF(E45="Uncommon",Rules!$B$19,Rules!$B$18))))*IF(U45="Y",Rules!$B$22,1),2) -> 9 | AA45: =Y45-Z45 -> 0 | AB45: =IF(E45="Starter",IF(AA45<0,"Starter (under on purpose)","Starter too strong"),IF(ABS(AA45)<=Rules!$B$25,"Balanced",IF(AA45>0,"Over budget","Under budget"))) -> Balanced
A46: C42 | B46: Barbed Dart | C46: Attack | D46: 1 | E46: Common | F46: Venom | G46: Deal 5 damage. Apply 3 Poison. | H46: Deal 6 damage. Apply 5 Poison. | I46: 5 | Q46: 3 | Y46: =ROUND((I46*Rules!$B$28+J46*Rules!$B$28*Rules!$B$24+K46*Rules!$B$29+L46*Rules!$B$30+M46*Rules!$B$31+N46*Rules!$B$32+(O46*Rules!$B$33+P46*Rules!$B$34+Q46*Rules!$B$35)*IF(R46="Y",Rules!$B$24,1)+S46*Rules!$B$36-T46*Rules!$B$37+IF(V46="Y",Rules!$B$38,0)+W46)*IF(C46="Power",Rules!$B$23,1),2) -> 9.5 | Z46: =ROUND((D46*Rules!$B$16+Rules!$B$17+IF(E46="Legendary",Rules!$B$21,IF(E46="Rare",Rules!$B$20,IF(E46="Uncommon",Rules!$B$19,Rules!$B$18))))*IF(U46="Y",Rules!$B$22,1),2) -> 9 | AA46: =Y46-Z46 -> 0.5 | AB46: =IF(E46="Starter",IF(AA46<0,"Starter (under on purpose)","Starter too strong"),IF(ABS(AA46)<=Rules!$B$25,"Balanced",IF(AA46>0,"Over budget","Under budget"))) -> Balanced
A47: C43 | B47: Snake Bite | C47: Attack | D47: 0 | E47: Common | F47: Venom | G47: Deal 1 damage. Apply 1 Poison. | H47: Deal 2 damage. Apply 2 Poison. | I47: 1 | Q47: 1 | Y47: =ROUND((I47*Rules!$B$28+J47*Rules!$B$28*Rules!$B$24+K47*Rules!$B$29+L47*Rules!$B$30+M47*Rules!$B$31+N47*Rules!$B$32+(O47*Rules!$B$33+P47*Rules!$B$34+Q47*Rules!$B$35)*IF(R47="Y",Rules!$B$24,1)+S47*Rules!$B$36-T47*Rules!$B$37+IF(V47="Y",Rules!$B$38,0)+W47)*IF(C47="Power",Rules!$B$23,1),2) -> 2.5 | Z47: =ROUND((D47*Rules!$B$16+Rules!$B$17+IF(E47="Legendary",Rules!$B$21,IF(E47="Rare",Rules!$B$20,IF(E47="Uncommon",Rules!$B$19,Rules!$B$18))))*IF(U47="Y",Rules!$B$22,1),2) -> 3 | AA47: =Y47-Z47 -> -0.5 | AB47: =IF(E47="Starter",IF(AA47<0,"Starter (under on purpose)","Starter too strong"),IF(ABS(AA47)<=Rules!$B$25,"Balanced",IF(AA47>0,"Over budget","Under budget"))) -> Balanced
A48: C44 | B48: Toxic Mist | C48: Skill | D48: 1 | E48: Common | F48: Venom | G48: Apply 4 Poison. Apply 1 Weak. | H48: Apply 6 Poison. Apply 1 Weak. | O48: 1 | Q48: 4 | Y48: =ROUND((I48*Rules!$B$28+J48*Rules!$B$28*Rules!$B$24+K48*Rules!$B$29+L48*Rules!$B$30+M48*Rules!$B$31+N48*Rules!$B$32+(O48*Rules!$B$33+P48*Rules!$B$34+Q48*Rules!$B$35)*IF(R48="Y",Rules!$B$24,1)+S48*Rules!$B$36-T48*Rules!$B$37+IF(V48="Y",Rules!$B$38,0)+W48)*IF(C48="Power",Rules!$B$23,1),2) -> 9 | Z48: =ROUND((D48*Rules!$B$16+Rules!$B$17+IF(E48="Legendary",Rules!$B$21,IF(E48="Rare",Rules!$B$20,IF(E48="Uncommon",Rules!$B$19,Rules!$B$18))))*IF(U48="Y",Rules!$B$22,1),2) -> 9 | AA48: =Y48-Z48 -> 0 | AB48: =IF(E48="Starter",IF(AA48<0,"Starter (under on purpose)","Starter too strong"),IF(ABS(AA48)<=Rules!$B$25,"Balanced",IF(AA48>0,"Over budget","Under budget"))) -> Balanced
A49: C45 | B49: Rotting Burst | C49: Attack | D49: 1 | E49: Common | F49: Venom | G49: Deal 4 damage to ALL enemies. Apply 2 Poison to ALL enemies. | H49: Deal 5 damage to ALL enemies. Apply 3 Poison to ALL enemies. | J49: 4 | Q49: 2 | R49: Y | Y49: =ROUND((I49*Rules!$B$28+J49*Rules!$B$28*Rules!$B$24+K49*Rules!$B$29+L49*Rules!$B$30+M49*Rules!$B$31+N49*Rules!$B$32+(O49*Rules!$B$33+P49*Rules!$B$34+Q49*Rules!$B$35)*IF(R49="Y",Rules!$B$24,1)+S49*Rules!$B$36-T49*Rules!$B$37+IF(V49="Y",Rules!$B$38,0)+W49)*IF(C49="Power",Rules!$B$23,1),2) -> 10.5 | Z49: =ROUND((D49*Rules!$B$16+Rules!$B$17+IF(E49="Legendary",Rules!$B$21,IF(E49="Rare",Rules!$B$20,IF(E49="Uncommon",Rules!$B$19,Rules!$B$18))))*IF(U49="Y",Rules!$B$22,1),2) -> 9 | AA49: =Y49-Z49 -> 1.5 | AB49: =IF(E49="Starter",IF(AA49<0,"Starter (under on purpose)","Starter too strong"),IF(ABS(AA49)<=Rules!$B$25,"Balanced",IF(AA49>0,"Over budget","Under budget"))) -> Balanced
A50: C46 | B50: Venom Ward | C50: Skill | D50: 1 | E50: Common | F50: Venom | G50: Gain 4 block. Apply 2 Poison to ALL enemies. | H50: Gain 6 block. Apply 3 Poison to ALL enemies. | K50: 4 | Q50: 2 | R50: Y | Y50: =ROUND((I50*Rules!$B$28+J50*Rules!$B$28*Rules!$B$24+K50*Rules!$B$29+L50*Rules!$B$30+M50*Rules!$B$31+N50*Rules!$B$32+(O50*Rules!$B$33+P50*Rules!$B$34+Q50*Rules!$B$35)*IF(R50="Y",Rules!$B$24,1)+S50*Rules!$B$36-T50*Rules!$B$37+IF(V50="Y",Rules!$B$38,0)+W50)*IF(C50="Power",Rules!$B$23,1),2) -> 9.3 | Z50: =ROUND((D50*Rules!$B$16+Rules!$B$17+IF(E50="Legendary",Rules!$B$21,IF(E50="Rare",Rules!$B$20,IF(E50="Uncommon",Rules!$B$19,Rules!$B$18))))*IF(U50="Y",Rules!$B$22,1),2) -> 9 | AA50: =Y50-Z50 -> 0.3 | AB50: =IF(E50="Starter",IF(AA50<0,"Starter (under on purpose)","Starter too strong"),IF(ABS(AA50)<=Rules!$B$25,"Balanced",IF(AA50>0,"Over budget","Under budget"))) -> Balanced
A51: C47 | B51: Creeping Rot | C51: Skill | D51: 0 | E51: Common | F51: Venom | G51: Apply 3 Poison. Exhaust. | H51: Apply 5 Poison. Exhaust. | Q51: 3 | U51: Y | Y51: =ROUND((I51*Rules!$B$28+J51*Rules!$B$28*Rules!$B$24+K51*Rules!$B$29+L51*Rules!$B$30+M51*Rules!$B$31+N51*Rules!$B$32+(O51*Rules!$B$33+P51*Rules!$B$34+Q51*Rules!$B$35)*IF(R51="Y",Rules!$B$24,1)+S51*Rules!$B$36-T51*Rules!$B$37+IF(V51="Y",Rules!$B$38,0)+W51)*IF(C51="Power",Rules!$B$23,1),2) -> 4.5 | Z51: =ROUND((D51*Rules!$B$16+Rules!$B$17+IF(E51="Legendary",Rules!$B$21,IF(E51="Rare",Rules!$B$20,IF(E51="Uncommon",Rules!$B$19,Rules!$B$18))))*IF(U51="Y",Rules!$B$22,1),2) -> 3.9 | AA51: =Y51-Z51 -> 0.6 | AB51: =IF(E51="Starter",IF(AA51<0,"Starter (under on purpose)","Starter too strong"),IF(ABS(AA51)<=Rules!$B$25,"Balanced",IF(AA51>0,"Over budget","Under budget"))) -> Balanced
A52: C48 | B52: Poison Shank | C52: Attack | D52: 1 | E52: Common | F52: Venom | G52: Deal 3 damage. Apply 2 Poison. Retain. | H52: Deal 4 damage. Apply 4 Poison. Retain. | I52: 3 | Q52: 2 | V52: Y | Y52: =ROUND((I52*Rules!$B$28+J52*Rules!$B$28*Rules!$B$24+K52*Rules!$B$29+L52*Rules!$B$30+M52*Rules!$B$31+N52*Rules!$B$32+(O52*Rules!$B$33+P52*Rules!$B$34+Q52*Rules!$B$35)*IF(R52="Y",Rules!$B$24,1)+S52*Rules!$B$36-T52*Rules!$B$37+IF(V52="Y",Rules!$B$38,0)+W52)*IF(C52="Power",Rules!$B$23,1),2) -> 8 | Z52: =ROUND((D52*Rules!$B$16+Rules!$B$17+IF(E52="Legendary",Rules!$B$21,IF(E52="Rare",Rules!$B$20,IF(E52="Uncommon",Rules!$B$19,Rules!$B$18))))*IF(U52="Y",Rules!$B$22,1),2) -> 9 | AA52: =Y52-Z52 -> -1 | AB52: =IF(E52="Starter",IF(AA52<0,"Starter (under on purpose)","Starter too strong"),IF(ABS(AA52)<=Rules!$B$25,"Balanced",IF(AA52>0,"Over budget","Under budget"))) -> Balanced
A53: C49 | B53: Size Up | C53: Skill | D53: 1 | E53: Common | F53: Tactician | G53: Draw 1 card. Apply 1 Weak and 1 Vulnerable. | H53: Draw 2 cards. Apply 1 Weak and 1 Vulnerable. | M53: 1 | O53: 1 | P53: 1 | Y53: =ROUND((I53*Rules!$B$28+J53*Rules!$B$28*Rules!$B$24+K53*Rules!$B$29+L53*Rules!$B$30+M53*Rules!$B$31+N53*Rules!$B$32+(O53*Rules!$B$33+P53*Rules!$B$34+Q53*Rules!$B$35)*IF(R53="Y",Rules!$B$24,1)+S53*Rules!$B$36-T53*Rules!$B$37+IF(V53="Y",Rules!$B$38,0)+W53)*IF(C53="Power",Rules!$B$23,1),2) -> 10 | Z53: =ROUND((D53*Rules!$B$16+Rules!$B$17+IF(E53="Legendary",Rules!$B$21,IF(E53="Rare",Rules!$B$20,IF(E53="Uncommon",Rules!$B$19,Rules!$B$18))))*IF(U53="Y",Rules!$B$22,1),2) -> 9 | AA53: =Y53-Z53 -> 1 | AB53: =IF(E53="Starter",IF(AA53<0,"Starter (under on purpose)","Starter too strong"),IF(ABS(AA53)<=Rules!$B$25,"Balanced",IF(AA53>0,"Over budget","Under budget"))) -> Balanced
A54: C50 | B54: Feint | C54: Skill | D54: 1 | E54: Common | F54: Tactician | G54: Gain 4 block. Apply 1 Weak to ALL enemies. | H54: Gain 6 block. Apply 2 Weak to ALL enemies. | K54: 4 | O54: 1 | R54: Y | Y54: =ROUND((I54*Rules!$B$28+J54*Rules!$B$28*Rules!$B$24+K54*Rules!$B$29+L54*Rules!$B$30+M54*Rules!$B$31+N54*Rules!$B$32+(O54*Rules!$B$33+P54*Rules!$B$34+Q54*Rules!$B$35)*IF(R54="Y",Rules!$B$24,1)+S54*Rules!$B$36-T54*Rules!$B$37+IF(V54="Y",Rules!$B$38,0)+W54)*IF(C54="Power",Rules!$B$23,1),2) -> 9.3 | Z54: =ROUND((D54*Rules!$B$16+Rules!$B$17+IF(E54="Legendary",Rules!$B$21,IF(E54="Rare",Rules!$B$20,IF(E54="Uncommon",Rules!$B$19,Rules!$B$18))))*IF(U54="Y",Rules!$B$22,1),2) -> 9 | AA54: =Y54-Z54 -> 0.3 | AB54: =IF(E54="Starter",IF(AA54<0,"Starter (under on purpose)","Starter too strong"),IF(ABS(AA54)<=Rules!$B$25,"Balanced",IF(AA54>0,"Over budget","Under budget"))) -> Balanced
A55: C51 | B55: Prepared Strike | C55: Attack | D55: 1 | E55: Common | F55: Tactician | G55: Deal 6 damage. Retain. | H55: Deal 9 damage. Retain. | I55: 6 | V55: Y | Y55: =ROUND((I55*Rules!$B$28+J55*Rules!$B$28*Rules!$B$24+K55*Rules!$B$29+L55*Rules!$B$30+M55*Rules!$B$31+N55*Rules!$B$32+(O55*Rules!$B$33+P55*Rules!$B$34+Q55*Rules!$B$35)*IF(R55="Y",Rules!$B$24,1)+S55*Rules!$B$36-T55*Rules!$B$37+IF(V55="Y",Rules!$B$38,0)+W55)*IF(C55="Power",Rules!$B$23,1),2) -> 8 | Z55: =ROUND((D55*Rules!$B$16+Rules!$B$17+IF(E55="Legendary",Rules!$B$21,IF(E55="Rare",Rules!$B$20,IF(E55="Uncommon",Rules!$B$19,Rules!$B$18))))*IF(U55="Y",Rules!$B$22,1),2) -> 9 | AA55: =Y55-Z55 -> -1 | AB55: =IF(E55="Starter",IF(AA55<0,"Starter (under on purpose)","Starter too strong"),IF(ABS(AA55)<=Rules!$B$25,"Balanced",IF(AA55>0,"Over budget","Under budget"))) -> Balanced
A56: C52 | B56: Trip Wire | C56: Skill | D56: 1 | E56: Common | F56: Tactician | G56: Gain 3 block. Apply 2 Vulnerable. | H56: Gain 5 block. Apply 3 Vulnerable. | K56: 3 | P56: 2 | Y56: =ROUND((I56*Rules!$B$28+J56*Rules!$B$28*Rules!$B$24+K56*Rules!$B$29+L56*Rules!$B$30+M56*Rules!$B$31+N56*Rules!$B$32+(O56*Rules!$B$33+P56*Rules!$B$34+Q56*Rules!$B$35)*IF(R56="Y",Rules!$B$24,1)+S56*Rules!$B$36-T56*Rules!$B$37+IF(V56="Y",Rules!$B$38,0)+W56)*IF(C56="Power",Rules!$B$23,1),2) -> 9.6 | Z56: =ROUND((D56*Rules!$B$16+Rules!$B$17+IF(E56="Legendary",Rules!$B$21,IF(E56="Rare",Rules!$B$20,IF(E56="Uncommon",Rules!$B$19,Rules!$B$18))))*IF(U56="Y",Rules!$B$22,1),2) -> 9 | AA56: =Y56-Z56 -> 0.6 | AB56: =IF(E56="Starter",IF(AA56<0,"Starter (under on purpose)","Starter too strong"),IF(ABS(AA56)<=Rules!$B$25,"Balanced",IF(AA56>0,"Over budget","Under budget"))) -> Balanced
A57: C53 | B57: Sift | C57: Skill | D57: 0 | E57: Common | F57: Tactician | G57: Draw 1 card, then discard 1. | H57: Draw 2 cards, then discard 1. | M57: 1 | W57: -1 | X57: Other: discard cost | Y57: =ROUND((I57*Rules!$B$28+J57*Rules!$B$28*Rules!$B$24+K57*Rules!$B$29+L57*Rules!$B$30+M57*Rules!$B$31+N57*Rules!$B$32+(O57*Rules!$B$33+P57*Rules!$B$34+Q57*Rules!$B$35)*IF(R57="Y",Rules!$B$24,1)+S57*Rules!$B$36-T57*Rules!$B$37+IF(V57="Y",Rules!$B$38,0)+W57)*IF(C57="Power",Rules!$B$23,1),2) -> 3 | Z57: =ROUND((D57*Rules!$B$16+Rules!$B$17+IF(E57="Legendary",Rules!$B$21,IF(E57="Rare",Rules!$B$20,IF(E57="Uncommon",Rules!$B$19,Rules!$B$18))))*IF(U57="Y",Rules!$B$22,1),2) -> 3 | AA57: =Y57-Z57 -> 0 | AB57: =IF(E57="Starter",IF(AA57<0,"Starter (under on purpose)","Starter too strong"),IF(ABS(AA57)<=Rules!$B$25,"Balanced",IF(AA57>0,"Over budget","Under budget"))) -> Balanced
A58: C54 | B58: Signal Flare | C58: Skill | D58: 1 | E58: Common | F58: Tactician | G58: Apply 1 Vulnerable to ALL enemies. Draw 1 card. | H58: Apply 2 Vulnerable to ALL enemies. Draw 1 card. | M58: 1 | P58: 1 | R58: Y | Y58: =ROUND((I58*Rules!$B$28+J58*Rules!$B$28*Rules!$B$24+K58*Rules!$B$29+L58*Rules!$B$30+M58*Rules!$B$31+N58*Rules!$B$32+(O58*Rules!$B$33+P58*Rules!$B$34+Q58*Rules!$B$35)*IF(R58="Y",Rules!$B$24,1)+S58*Rules!$B$36-T58*Rules!$B$37+IF(V58="Y",Rules!$B$38,0)+W58)*IF(C58="Power",Rules!$B$23,1),2) -> 8.5 | Z58: =ROUND((D58*Rules!$B$16+Rules!$B$17+IF(E58="Legendary",Rules!$B$21,IF(E58="Rare",Rules!$B$20,IF(E58="Uncommon",Rules!$B$19,Rules!$B$18))))*IF(U58="Y",Rules!$B$22,1),2) -> 9 | AA58: =Y58-Z58 -> -0.5 | AB58: =IF(E58="Starter",IF(AA58<0,"Starter (under on purpose)","Starter too strong"),IF(ABS(AA58)<=Rules!$B$25,"Balanced",IF(AA58>0,"Over budget","Under budget"))) -> Balanced
A59: C55 | B59: Calculated Blow | C59: Attack | D59: 2 | E59: Common | F59: Tactician | G59: Deal 10 damage. Draw 1 card. | H59: Deal 14 damage. Draw 1 card. | I59: 10 | M59: 1 | Y59: =ROUND((I59*Rules!$B$28+J59*Rules!$B$28*Rules!$B$24+K59*Rules!$B$29+L59*Rules!$B$30+M59*Rules!$B$31+N59*Rules!$B$32+(O59*Rules!$B$33+P59*Rules!$B$34+Q59*Rules!$B$35)*IF(R59="Y",Rules!$B$24,1)+S59*Rules!$B$36-T59*Rules!$B$37+IF(V59="Y",Rules!$B$38,0)+W59)*IF(C59="Power",Rules!$B$23,1),2) -> 14 | Z59: =ROUND((D59*Rules!$B$16+Rules!$B$17+IF(E59="Legendary",Rules!$B$21,IF(E59="Rare",Rules!$B$20,IF(E59="Uncommon",Rules!$B$19,Rules!$B$18))))*IF(U59="Y",Rules!$B$22,1),2) -> 15 | AA59: =Y59-Z59 -> -1 | AB59: =IF(E59="Starter",IF(AA59<0,"Starter (under on purpose)","Starter too strong"),IF(ABS(AA59)<=Rules!$B$25,"Balanced",IF(AA59>0,"Over budget","Under budget"))) -> Balanced
A60: U01 | B60: Expose | C60: Attack | D60: 1 | E60: Uncommon | F60: Tactician | G60: Deal 5 damage. Apply 2 Vulnerable. | H60: Deal 7 damage. Apply 3 Vulnerable. | I60: 5 | P60: 2 | Y60: =ROUND((I60*Rules!$B$28+J60*Rules!$B$28*Rules!$B$24+K60*Rules!$B$29+L60*Rules!$B$30+M60*Rules!$B$31+N60*Rules!$B$32+(O60*Rules!$B$33+P60*Rules!$B$34+Q60*Rules!$B$35)*IF(R60="Y",Rules!$B$24,1)+S60*Rules!$B$36-T60*Rules!$B$37+IF(V60="Y",Rules!$B$38,0)+W60)*IF(C60="Power",Rules!$B$23,1),2) -> 11 | Z60: =ROUND((D60*Rules!$B$16+Rules!$B$17+IF(E60="Legendary",Rules!$B$21,IF(E60="Rare",Rules!$B$20,IF(E60="Uncommon",Rules!$B$19,Rules!$B$18))))*IF(U60="Y",Rules!$B$22,1),2) -> 11 | AA60: =Y60-Z60 -> 0 | AB60: =IF(E60="Starter",IF(AA60<0,"Starter (under on purpose)","Starter too strong"),IF(ABS(AA60)<=Rules!$B$25,"Balanced",IF(AA60>0,"Over budget","Under budget"))) -> Balanced
A61: U02 | B61: Shield Bash | C61: Attack | D61: 2 | E61: Uncommon | F61: Guardian | G61: Deal 8 damage. Gain 7 block. | H61: Deal 11 damage. Gain 9 block. | I61: 8 | K61: 7 | Y61: =ROUND((I61*Rules!$B$28+J61*Rules!$B$28*Rules!$B$24+K61*Rules!$B$29+L61*Rules!$B$30+M61*Rules!$B$31+N61*Rules!$B$32+(O61*Rules!$B$33+P61*Rules!$B$34+Q61*Rules!$B$35)*IF(R61="Y",Rules!$B$24,1)+S61*Rules!$B$36-T61*Rules!$B$37+IF(V61="Y",Rules!$B$38,0)+W61)*IF(C61="Power",Rules!$B$23,1),2) -> 16.4 | Z61: =ROUND((D61*Rules!$B$16+Rules!$B$17+IF(E61="Legendary",Rules!$B$21,IF(E61="Rare",Rules!$B$20,IF(E61="Uncommon",Rules!$B$19,Rules!$B$18))))*IF(U61="Y",Rules!$B$22,1),2) -> 17 | AA61: =Y61-Z61 -> -0.6 | AB61: =IF(E61="Starter",IF(AA61<0,"Starter (under on purpose)","Starter too strong"),IF(ABS(AA61)<=Rules!$B$25,"Balanced",IF(AA61>0,"Over budget","Under budget"))) -> Balanced
A62: U03 | B62: Whirling Blade | C62: Attack | D62: 2 | E62: Uncommon | F62: Brawler | G62: Deal 11 damage to ALL enemies. | H62: Deal 15 damage to ALL enemies. | J62: 11 | Y62: =ROUND((I62*Rules!$B$28+J62*Rules!$B$28*Rules!$B$24+K62*Rules!$B$29+L62*Rules!$B$30+M62*Rules!$B$31+N62*Rules!$B$32+(O62*Rules!$B$33+P62*Rules!$B$34+Q62*Rules!$B$35)*IF(R62="Y",Rules!$B$24,1)+S62*Rules!$B$36-T62*Rules!$B$37+IF(V62="Y",Rules!$B$38,0)+W62)*IF(C62="Power",Rules!$B$23,1),2) -> 16.5 | Z62: =ROUND((D62*Rules!$B$16+Rules!$B$17+IF(E62="Legendary",Rules!$B$21,IF(E62="Rare",Rules!$B$20,IF(E62="Uncommon",Rules!$B$19,Rules!$B$18))))*IF(U62="Y",Rules!$B$22,1),2) -> 17 | AA62: =Y62-Z62 -> -0.5 | AB62: =IF(E62="Starter",IF(AA62<0,"Starter (under on purpose)","Starter too strong"),IF(ABS(AA62)<=Rules!$B$25,"Balanced",IF(AA62>0,"Over budget","Under budget"))) -> Balanced
A63: U04 | B63: Venom Cloud | C63: Skill | D63: 2 | E63: Uncommon | F63: Venom | G63: Apply 7 Poison to ALL enemies. | H63: Apply 10 Poison to ALL enemies. | Q63: 7 | R63: Y | Y63: =ROUND((I63*Rules!$B$28+J63*Rules!$B$28*Rules!$B$24+K63*Rules!$B$29+L63*Rules!$B$30+M63*Rules!$B$31+N63*Rules!$B$32+(O63*Rules!$B$33+P63*Rules!$B$34+Q63*Rules!$B$35)*IF(R63="Y",Rules!$B$24,1)+S63*Rules!$B$36-T63*Rules!$B$37+IF(V63="Y",Rules!$B$38,0)+W63)*IF(C63="Power",Rules!$B$23,1),2) -> 15.75 | Z63: =ROUND((D63*Rules!$B$16+Rules!$B$17+IF(E63="Legendary",Rules!$B$21,IF(E63="Rare",Rules!$B$20,IF(E63="Uncommon",Rules!$B$19,Rules!$B$18))))*IF(U63="Y",Rules!$B$22,1),2) -> 17 | AA63: =Y63-Z63 -> -1.25 | AB63: =IF(E63="Starter",IF(AA63<0,"Starter (under on purpose)","Starter too strong"),IF(ABS(AA63)<=Rules!$B$25,"Balanced",IF(AA63>0,"Over budget","Under budget"))) -> Balanced
A64: U05 | B64: Rally | C64: Skill | D64: 0 | E64: Uncommon | F64: Tactician | G64: Gain 1 energy. Exhaust. | H64: Gain 1 energy. Draw 1 card. Exhaust. | N64: 1 | U64: Y | Y64: =ROUND((I64*Rules!$B$28+J64*Rules!$B$28*Rules!$B$24+K64*Rules!$B$29+L64*Rules!$B$30+M64*Rules!$B$31+N64*Rules!$B$32+(O64*Rules!$B$33+P64*Rules!$B$34+Q64*Rules!$B$35)*IF(R64="Y",Rules!$B$24,1)+S64*Rules!$B$36-T64*Rules!$B$37+IF(V64="Y",Rules!$B$38,0)+W64)*IF(C64="Power",Rules!$B$23,1),2) -> 6 | Z64: =ROUND((D64*Rules!$B$16+Rules!$B$17+IF(E64="Legendary",Rules!$B$21,IF(E64="Rare",Rules!$B$20,IF(E64="Uncommon",Rules!$B$19,Rules!$B$18))))*IF(U64="Y",Rules!$B$22,1),2) -> 6.5 | AA64: =Y64-Z64 -> -0.5 | AB64: =IF(E64="Starter",IF(AA64<0,"Starter (under on purpose)","Starter too strong"),IF(ABS(AA64)<=Rules!$B$25,"Balanced",IF(AA64>0,"Over budget","Under budget"))) -> Balanced
A65: U06 | B65: Iron Skin | C65: Power | D65: 1 | E65: Uncommon | F65: Guardian | G65: At the start of each turn, gain 4 block. | H65: At the start of each turn, gain 6 block. | K65: 4 | X65: Power: per-turn effect | Y65: =ROUND((I65*Rules!$B$28+J65*Rules!$B$28*Rules!$B$24+K65*Rules!$B$29+L65*Rules!$B$30+M65*Rules!$B$31+N65*Rules!$B$32+(O65*Rules!$B$33+P65*Rules!$B$34+Q65*Rules!$B$35)*IF(R65="Y",Rules!$B$24,1)+S65*Rules!$B$36-T65*Rules!$B$37+IF(V65="Y",Rules!$B$38,0)+W65)*IF(C65="Power",Rules!$B$23,1),2) -> 9.6 | Z65: =ROUND((D65*Rules!$B$16+Rules!$B$17+IF(E65="Legendary",Rules!$B$21,IF(E65="Rare",Rules!$B$20,IF(E65="Uncommon",Rules!$B$19,Rules!$B$18))))*IF(U65="Y",Rules!$B$22,1),2) -> 11 | AA65: =Y65-Z65 -> -1.4 | AB65: =IF(E65="Starter",IF(AA65<0,"Starter (under on purpose)","Starter too strong"),IF(ABS(AA65)<=Rules!$B$25,"Balanced",IF(AA65>0,"Over budget","Under budget"))) -> Balanced
A66: U07 | B66: Battle Cry | C66: Skill | D66: 1 | E66: Uncommon | F66: Brawler | G66: Gain 2 Strength. Draw 1 card. | H66: Gain 3 Strength. Draw 1 card. | M66: 1 | S66: 2 | X66: Core Brawler engine | Y66: =ROUND((I66*Rules!$B$28+J66*Rules!$B$28*Rules!$B$24+K66*Rules!$B$29+L66*Rules!$B$30+M66*Rules!$B$31+N66*Rules!$B$32+(O66*Rules!$B$33+P66*Rules!$B$34+Q66*Rules!$B$35)*IF(R66="Y",Rules!$B$24,1)+S66*Rules!$B$36-T66*Rules!$B$37+IF(V66="Y",Rules!$B$38,0)+W66)*IF(C66="Power",Rules!$B$23,1),2) -> 12 | Z66: =ROUND((D66*Rules!$B$16+Rules!$B$17+IF(E66="Legendary",Rules!$B$21,IF(E66="Rare",Rules!$B$20,IF(E66="Uncommon",Rules!$B$19,Rules!$B$18))))*IF(U66="Y",Rules!$B$22,1),2) -> 11 | AA66: =Y66-Z66 -> 1 | AB66: =IF(E66="Starter",IF(AA66<0,"Starter (under on purpose)","Starter too strong"),IF(ABS(AA66)<=Rules!$B$25,"Balanced",IF(AA66>0,"Over budget","Under budget"))) -> Balanced
A67: U08 | B67: Bloodletter | C67: Attack | D67: 2 | E67: Uncommon | F67: Brawler | G67: Deal 12 damage. If this kills an enemy, heal 5 HP. | H67: Deal 15 damage. If this kills an enemy, heal 7 HP. | I67: 12 | W67: 4 | X67: Other: conditional heal (~half of 5 heal) | Y67: =ROUND((I67*Rules!$B$28+J67*Rules!$B$28*Rules!$B$24+K67*Rules!$B$29+L67*Rules!$B$30+M67*Rules!$B$31+N67*Rules!$B$32+(O67*Rules!$B$33+P67*Rules!$B$34+Q67*Rules!$B$35)*IF(R67="Y",Rules!$B$24,1)+S67*Rules!$B$36-T67*Rules!$B$37+IF(V67="Y",Rules!$B$38,0)+W67)*IF(C67="Power",Rules!$B$23,1),2) -> 16 | Z67: =ROUND((D67*Rules!$B$16+Rules!$B$17+IF(E67="Legendary",Rules!$B$21,IF(E67="Rare",Rules!$B$20,IF(E67="Uncommon",Rules!$B$19,Rules!$B$18))))*IF(U67="Y",Rules!$B$22,1),2) -> 17 | AA67: =Y67-Z67 -> -1 | AB67: =IF(E67="Starter",IF(AA67<0,"Starter (under on purpose)","Starter too strong"),IF(ABS(AA67)<=Rules!$B$25,"Balanced",IF(AA67>0,"Over budget","Under budget"))) -> Balanced
A68: U09 | B68: Envenom | C68: Power | D68: 1 | E68: Uncommon | F68: Venom | G68: Whenever your Attack deals damage, apply 1 Poison. | H68: Whenever your Attack deals damage, apply 2 Poison. | W68: 5.5 | X68: PLAYTEST: value depends on attacks per turn | Y68: =ROUND((I68*Rules!$B$28+J68*Rules!$B$28*Rules!$B$24+K68*Rules!$B$29+L68*Rules!$B$30+M68*Rules!$B$31+N68*Rules!$B$32+(O68*Rules!$B$33+P68*Rules!$B$34+Q68*Rules!$B$35)*IF(R68="Y",Rules!$B$24,1)+S68*Rules!$B$36-T68*Rules!$B$37+IF(V68="Y",Rules!$B$38,0)+W68)*IF(C68="Power",Rules!$B$23,1),2) -> 11 | Z68: =ROUND((D68*Rules!$B$16+Rules!$B$17+IF(E68="Legendary",Rules!$B$21,IF(E68="Rare",Rules!$B$20,IF(E68="Uncommon",Rules!$B$19,Rules!$B$18))))*IF(U68="Y",Rules!$B$22,1),2) -> 11 | AA68: =Y68-Z68 -> 0 | AB68: =IF(E68="Starter",IF(AA68<0,"Starter (under on purpose)","Starter too strong"),IF(ABS(AA68)<=Rules!$B$25,"Balanced",IF(AA68>0,"Over budget","Under budget"))) -> Balanced
A69: U10 | B69: Parry | C69: Skill | D69: 1 | E69: Uncommon | F69: Guardian | G69: Gain 6 block. If the enemy intends to attack, deal 5 damage to it. | H69: Gain 8 block. If the enemy intends to attack, deal 8 damage to it. | K69: 6 | W69: 3.5 | X69: Uses enemy intent (Role 1) | Y69: =ROUND((I69*Rules!$B$28+J69*Rules!$B$28*Rules!$B$24+K69*Rules!$B$29+L69*Rules!$B$30+M69*Rules!$B$31+N69*Rules!$B$32+(O69*Rules!$B$33+P69*Rules!$B$34+Q69*Rules!$B$35)*IF(R69="Y",Rules!$B$24,1)+S69*Rules!$B$36-T69*Rules!$B$37+IF(V69="Y",Rules!$B$38,0)+W69)*IF(C69="Power",Rules!$B$23,1),2) -> 10.7 | Z69: =ROUND((D69*Rules!$B$16+Rules!$B$17+IF(E69="Legendary",Rules!$B$21,IF(E69="Rare",Rules!$B$20,IF(E69="Uncommon",Rules!$B$19,Rules!$B$18))))*IF(U69="Y",Rules!$B$22,1),2) -> 11 | AA69: =Y69-Z69 -> -0.3 | AB69: =IF(E69="Starter",IF(AA69<0,"Starter (under on purpose)","Starter too strong"),IF(ABS(AA69)<=Rules!$B$25,"Balanced",IF(AA69>0,"Over budget","Under budget"))) -> Balanced
A70: U11 | B70: Reckless Charge | C70: Attack | D70: 0 | E70: Uncommon | F70: Brawler | G70: Deal 8 damage. Lose 2 HP. | H70: Deal 11 damage. Lose 2 HP. | I70: 8 | T70: 2 | Y70: =ROUND((I70*Rules!$B$28+J70*Rules!$B$28*Rules!$B$24+K70*Rules!$B$29+L70*Rules!$B$30+M70*Rules!$B$31+N70*Rules!$B$32+(O70*Rules!$B$33+P70*Rules!$B$34+Q70*Rules!$B$35)*IF(R70="Y",Rules!$B$24,1)+S70*Rules!$B$36-T70*Rules!$B$37+IF(V70="Y",Rules!$B$38,0)+W70)*IF(C70="Power",Rules!$B$23,1),2) -> 5 | Z70: =ROUND((D70*Rules!$B$16+Rules!$B$17+IF(E70="Legendary",Rules!$B$21,IF(E70="Rare",Rules!$B$20,IF(E70="Uncommon",Rules!$B$19,Rules!$B$18))))*IF(U70="Y",Rules!$B$22,1),2) -> 5 | AA70: =Y70-Z70 -> 0 | AB70: =IF(E70="Starter",IF(AA70<0,"Starter (under on purpose)","Starter too strong"),IF(ABS(AA70)<=Rules!$B$25,"Balanced",IF(AA70>0,"Over budget","Under budget"))) -> Balanced
A71: U12 | B71: Quick Thinking | C71: Skill | D71: 1 | E71: Uncommon | F71: Tactician | G71: Draw 3 cards, then discard 1. | H71: Draw 4 cards, then discard 1. | M71: 3 | W71: -1 | X71: Other: discard cost; needs choose-a-card UI (Role 3) | Y71: =ROUND((I71*Rules!$B$28+J71*Rules!$B$28*Rules!$B$24+K71*Rules!$B$29+L71*Rules!$B$30+M71*Rules!$B$31+N71*Rules!$B$32+(O71*Rules!$B$33+P71*Rules!$B$34+Q71*Rules!$B$35)*IF(R71="Y",Rules!$B$24,1)+S71*Rules!$B$36-T71*Rules!$B$37+IF(V71="Y",Rules!$B$38,0)+W71)*IF(C71="Power",Rules!$B$23,1),2) -> 11 | Z71: =ROUND((D71*Rules!$B$16+Rules!$B$17+IF(E71="Legendary",Rules!$B$21,IF(E71="Rare",Rules!$B$20,IF(E71="Uncommon",Rules!$B$19,Rules!$B$18))))*IF(U71="Y",Rules!$B$22,1),2) -> 11 | AA71: =Y71-Z71 -> 0 | AB71: =IF(E71="Starter",IF(AA71<0,"Starter (under on purpose)","Starter too strong"),IF(ABS(AA71)<=Rules!$B$25,"Balanced",IF(AA71>0,"Over budget","Under budget"))) -> Balanced
A72: U13 | B72: Bulwark | C72: Skill | D72: 2 | E72: Uncommon | F72: Guardian | G72: Gain 10 block. Next turn, gain 5 block. | H72: Gain 13 block. Next turn, gain 7 block. | K72: 15 | X72: Block column = 10 now + 5 next turn | Y72: =ROUND((I72*Rules!$B$28+J72*Rules!$B$28*Rules!$B$24+K72*Rules!$B$29+L72*Rules!$B$30+M72*Rules!$B$31+N72*Rules!$B$32+(O72*Rules!$B$33+P72*Rules!$B$34+Q72*Rules!$B$35)*IF(R72="Y",Rules!$B$24,1)+S72*Rules!$B$36-T72*Rules!$B$37+IF(V72="Y",Rules!$B$38,0)+W72)*IF(C72="Power",Rules!$B$23,1),2) -> 18 | Z72: =ROUND((D72*Rules!$B$16+Rules!$B$17+IF(E72="Legendary",Rules!$B$21,IF(E72="Rare",Rules!$B$20,IF(E72="Uncommon",Rules!$B$19,Rules!$B$18))))*IF(U72="Y",Rules!$B$22,1),2) -> 17 | AA72: =Y72-Z72 -> 1 | AB72: =IF(E72="Starter",IF(AA72<0,"Starter (under on purpose)","Starter too strong"),IF(ABS(AA72)<=Rules!$B$25,"Balanced",IF(AA72>0,"Over budget","Under budget"))) -> Balanced
A73: U14 | B73: Catalyst | C73: Skill | D73: 1 | E73: Uncommon | F73: Venom | G73: Double an enemy's Poison. Exhaust. | H73: Triple an enemy's Poison. Exhaust. | U73: Y | W73: 14 | X73: PLAYTEST: scales with existing Poison | Y73: =ROUND((I73*Rules!$B$28+J73*Rules!$B$28*Rules!$B$24+K73*Rules!$B$29+L73*Rules!$B$30+M73*Rules!$B$31+N73*Rules!$B$32+(O73*Rules!$B$33+P73*Rules!$B$34+Q73*Rules!$B$35)*IF(R73="Y",Rules!$B$24,1)+S73*Rules!$B$36-T73*Rules!$B$37+IF(V73="Y",Rules!$B$38,0)+W73)*IF(C73="Power",Rules!$B$23,1),2) -> 14 | Z73: =ROUND((D73*Rules!$B$16+Rules!$B$17+IF(E73="Legendary",Rules!$B$21,IF(E73="Rare",Rules!$B$20,IF(E73="Uncommon",Rules!$B$19,Rules!$B$18))))*IF(U73="Y",Rules!$B$22,1),2) -> 14.3 | AA73: =Y73-Z73 -> -0.3 | AB73: =IF(E73="Starter",IF(AA73<0,"Starter (under on purpose)","Starter too strong"),IF(ABS(AA73)<=Rules!$B$25,"Balanced",IF(AA73>0,"Over budget","Under budget"))) -> Balanced
A74: U15 | B74: Field Medic | C74: Skill | D74: 1 | E74: Uncommon | F74: Neutral | G74: Heal 3 HP. Gain 6 block. | H74: Heal 5 HP. Gain 7 block. | K74: 6 | L74: 3 | Y74: =ROUND((I74*Rules!$B$28+J74*Rules!$B$28*Rules!$B$24+K74*Rules!$B$29+L74*Rules!$B$30+M74*Rules!$B$31+N74*Rules!$B$32+(O74*Rules!$B$33+P74*Rules!$B$34+Q74*Rules!$B$35)*IF(R74="Y",Rules!$B$24,1)+S74*Rules!$B$36-T74*Rules!$B$37+IF(V74="Y",Rules!$B$38,0)+W74)*IF(C74="Power",Rules!$B$23,1),2) -> 11.7 | Z74: =ROUND((D74*Rules!$B$16+Rules!$B$17+IF(E74="Legendary",Rules!$B$21,IF(E74="Rare",Rules!$B$20,IF(E74="Uncommon",Rules!$B$19,Rules!$B$18))))*IF(U74="Y",Rules!$B$22,1),2) -> 11 | AA74: =Y74-Z74 -> 0.7 | AB74: =IF(E74="Starter",IF(AA74<0,"Starter (under on purpose)","Starter too strong"),IF(ABS(AA74)<=Rules!$B$25,"Balanced",IF(AA74>0,"Over budget","Under budget"))) -> Balanced
A75: U16 | B75: Lucky Find | C75: Skill | D75: 0 | E75: Uncommon | F75: Neutral | G75: Draw 2 cards. Exhaust. | H75: Draw 3 cards. Exhaust. | M75: 2 | U75: Y | Y75: =ROUND((I75*Rules!$B$28+J75*Rules!$B$28*Rules!$B$24+K75*Rules!$B$29+L75*Rules!$B$30+M75*Rules!$B$31+N75*Rules!$B$32+(O75*Rules!$B$33+P75*Rules!$B$34+Q75*Rules!$B$35)*IF(R75="Y",Rules!$B$24,1)+S75*Rules!$B$36-T75*Rules!$B$37+IF(V75="Y",Rules!$B$38,0)+W75)*IF(C75="Power",Rules!$B$23,1),2) -> 8 | Z75: =ROUND((D75*Rules!$B$16+Rules!$B$17+IF(E75="Legendary",Rules!$B$21,IF(E75="Rare",Rules!$B$20,IF(E75="Uncommon",Rules!$B$19,Rules!$B$18))))*IF(U75="Y",Rules!$B$22,1),2) -> 6.5 | AA75: =Y75-Z75 -> 1.5 | AB75: =IF(E75="Starter",IF(AA75<0,"Starter (under on purpose)","Starter too strong"),IF(ABS(AA75)<=Rules!$B$25,"Balanced",IF(AA75>0,"Over budget","Under budget"))) -> Balanced
A76: U17 | B76: Map of the Depths | C76: Power | D76: 1 | E76: Uncommon | F76: Neutral | G76: At the start of your turn, draw 1 extra card. | H76: Costs 0. At the start of your turn, draw 1 extra card. | M76: 1 | W76: 1.5 | X76: NEW power: draw_per_turn. PLAYTEST: card draw engines snowball | Y76: =ROUND((I76*Rules!$B$28+J76*Rules!$B$28*Rules!$B$24+K76*Rules!$B$29+L76*Rules!$B$30+M76*Rules!$B$31+N76*Rules!$B$32+(O76*Rules!$B$33+P76*Rules!$B$34+Q76*Rules!$B$35)*IF(R76="Y",Rules!$B$24,1)+S76*Rules!$B$36-T76*Rules!$B$37+IF(V76="Y",Rules!$B$38,0)+W76)*IF(C76="Power",Rules!$B$23,1),2) -> 11 | Z76: =ROUND((D76*Rules!$B$16+Rules!$B$17+IF(E76="Legendary",Rules!$B$21,IF(E76="Rare",Rules!$B$20,IF(E76="Uncommon",Rules!$B$19,Rules!$B$18))))*IF(U76="Y",Rules!$B$22,1),2) -> 11 | AA76: =Y76-Z76 -> 0 | AB76: =IF(E76="Starter",IF(AA76<0,"Starter (under on purpose)","Starter too strong"),IF(ABS(AA76)<=Rules!$B$25,"Balanced",IF(AA76>0,"Over budget","Under budget"))) -> Balanced
A77: U18 | B77: Cleaving Fury | C77: Attack | D77: 1 | E77: Uncommon | F77: Brawler | G77: Deal 5 damage to ALL enemies. Gain 1 Strength. | H77: Deal 7 damage to ALL enemies. Gain 1 Strength. | J77: 5 | S77: 1 | Y77: =ROUND((I77*Rules!$B$28+J77*Rules!$B$28*Rules!$B$24+K77*Rules!$B$29+L77*Rules!$B$30+M77*Rules!$B$31+N77*Rules!$B$32+(O77*Rules!$B$33+P77*Rules!$B$34+Q77*Rules!$B$35)*IF(R77="Y",Rules!$B$24,1)+S77*Rules!$B$36-T77*Rules!$B$37+IF(V77="Y",Rules!$B$38,0)+W77)*IF(C77="Power",Rules!$B$23,1),2) -> 11.5 | Z77: =ROUND((D77*Rules!$B$16+Rules!$B$17+IF(E77="Legendary",Rules!$B$21,IF(E77="Rare",Rules!$B$20,IF(E77="Uncommon",Rules!$B$19,Rules!$B$18))))*IF(U77="Y",Rules!$B$22,1),2) -> 11 | AA77: =Y77-Z77 -> 0.5 | AB77: =IF(E77="Starter",IF(AA77<0,"Starter (under on purpose)","Starter too strong"),IF(ABS(AA77)<=Rules!$B$25,"Balanced",IF(AA77>0,"Over budget","Under budget"))) -> Balanced
A78: U19 | B78: Bloodlust | C78: Power | D78: 2 | E78: Uncommon | F78: Brawler | G78: At the start of your turn, gain 1 Strength. | H78: Costs 1. At the start of your turn, gain 1 Strength. | S78: 1 | W78: 4.5 | X78: NEW power: strength_per_turn. PLAYTEST: ramps every turn | Y78: =ROUND((I78*Rules!$B$28+J78*Rules!$B$28*Rules!$B$24+K78*Rules!$B$29+L78*Rules!$B$30+M78*Rules!$B$31+N78*Rules!$B$32+(O78*Rules!$B$33+P78*Rules!$B$34+Q78*Rules!$B$35)*IF(R78="Y",Rules!$B$24,1)+S78*Rules!$B$36-T78*Rules!$B$37+IF(V78="Y",Rules!$B$38,0)+W78)*IF(C78="Power",Rules!$B$23,1),2) -> 17 | Z78: =ROUND((D78*Rules!$B$16+Rules!$B$17+IF(E78="Legendary",Rules!$B$21,IF(E78="Rare",Rules!$B$20,IF(E78="Uncommon",Rules!$B$19,Rules!$B$18))))*IF(U78="Y",Rules!$B$22,1),2) -> 17 | AA78: =Y78-Z78 -> 0 | AB78: =IF(E78="Starter",IF(AA78<0,"Starter (under on purpose)","Starter too strong"),IF(ABS(AA78)<=Rules!$B$25,"Balanced",IF(AA78>0,"Over budget","Under budget"))) -> Balanced
A79: U20 | B79: Pummel | C79: Attack | D79: 1 | E79: Uncommon | F79: Brawler | G79: Deal 3 damage 4 times. Exhaust. | H79: Deal 4 damage 4 times. Exhaust. | I79: 12 | U79: Y | W79: 1.5 | X79: Other: 4 hits quadruple Strength bonus | Y79: =ROUND((I79*Rules!$B$28+J79*Rules!$B$28*Rules!$B$24+K79*Rules!$B$29+L79*Rules!$B$30+M79*Rules!$B$31+N79*Rules!$B$32+(O79*Rules!$B$33+P79*Rules!$B$34+Q79*Rules!$B$35)*IF(R79="Y",Rules!$B$24,1)+S79*Rules!$B$36-T79*Rules!$B$37+IF(V79="Y",Rules!$B$38,0)+W79)*IF(C79="Power",Rules!$B$23,1),2) -> 13.5 | Z79: =ROUND((D79*Rules!$B$16+Rules!$B$17+IF(E79="Legendary",Rules!$B$21,IF(E79="Rare",Rules!$B$20,IF(E79="Uncommon",Rules!$B$19,Rules!$B$18))))*IF(U79="Y",Rules!$B$22,1),2) -> 14.3 | AA79: =Y79-Z79 -> -0.8 | AB79: =IF(E79="Starter",IF(AA79<0,"Starter (under on purpose)","Starter too strong"),IF(ABS(AA79)<=Rules!$B$25,"Balanced",IF(AA79>0,"Over budget","Under budget"))) -> Balanced
A80: U21 | B80: Haymaker | C80: Attack | D80: 2 | E80: Uncommon | F80: Brawler | G80: Deal 14 damage. Apply 1 Weak. | H80: Deal 18 damage. Apply 2 Weak. | I80: 14 | O80: 1 | Y80: =ROUND((I80*Rules!$B$28+J80*Rules!$B$28*Rules!$B$24+K80*Rules!$B$29+L80*Rules!$B$30+M80*Rules!$B$31+N80*Rules!$B$32+(O80*Rules!$B$33+P80*Rules!$B$34+Q80*Rules!$B$35)*IF(R80="Y",Rules!$B$24,1)+S80*Rules!$B$36-T80*Rules!$B$37+IF(V80="Y",Rules!$B$38,0)+W80)*IF(C80="Power",Rules!$B$23,1),2) -> 17 | Z80: =ROUND((D80*Rules!$B$16+Rules!$B$17+IF(E80="Legendary",Rules!$B$21,IF(E80="Rare",Rules!$B$20,IF(E80="Uncommon",Rules!$B$19,Rules!$B$18))))*IF(U80="Y",Rules!$B$22,1),2) -> 17 | AA80: =Y80-Z80 -> 0 | AB80: =IF(E80="Starter",IF(AA80<0,"Starter (under on purpose)","Starter too strong"),IF(ABS(AA80)<=Rules!$B$25,"Balanced",IF(AA80>0,"Over budget","Under budget"))) -> Balanced
A81: U22 | B81: Reckless Smash | C81: Attack | D81: 2 | E81: Uncommon | F81: Brawler | G81: Deal 20 damage. Lose 2 HP. | H81: Deal 26 damage. Lose 2 HP. | I81: 20 | T81: 2 | Y81: =ROUND((I81*Rules!$B$28+J81*Rules!$B$28*Rules!$B$24+K81*Rules!$B$29+L81*Rules!$B$30+M81*Rules!$B$31+N81*Rules!$B$32+(O81*Rules!$B$33+P81*Rules!$B$34+Q81*Rules!$B$35)*IF(R81="Y",Rules!$B$24,1)+S81*Rules!$B$36-T81*Rules!$B$37+IF(V81="Y",Rules!$B$38,0)+W81)*IF(C81="Power",Rules!$B$23,1),2) -> 17 | Z81: =ROUND((D81*Rules!$B$16+Rules!$B$17+IF(E81="Legendary",Rules!$B$21,IF(E81="Rare",Rules!$B$20,IF(E81="Uncommon",Rules!$B$19,Rules!$B$18))))*IF(U81="Y",Rules!$B$22,1),2) -> 17 | AA81: =Y81-Z81 -> 0 | AB81: =IF(E81="Starter",IF(AA81<0,"Starter (under on purpose)","Starter too strong"),IF(ABS(AA81)<=Rules!$B$25,"Balanced",IF(AA81>0,"Over budget","Under budget"))) -> Balanced
A82: U23 | B82: Entrench | C82: Skill | D82: 2 | E82: Uncommon | F82: Guardian | G82: Double your block. | H82: Costs 1. Double your block. | W82: 16.5 | X82: NEW: multiply_block. PLAYTEST: value depends on current block | Y82: =ROUND((I82*Rules!$B$28+J82*Rules!$B$28*Rules!$B$24+K82*Rules!$B$29+L82*Rules!$B$30+M82*Rules!$B$31+N82*Rules!$B$32+(O82*Rules!$B$33+P82*Rules!$B$34+Q82*Rules!$B$35)*IF(R82="Y",Rules!$B$24,1)+S82*Rules!$B$36-T82*Rules!$B$37+IF(V82="Y",Rules!$B$38,0)+W82)*IF(C82="Power",Rules!$B$23,1),2) -> 16.5 | Z82: =ROUND((D82*Rules!$B$16+Rules!$B$17+IF(E82="Legendary",Rules!$B$21,IF(E82="Rare",Rules!$B$20,IF(E82="Uncommon",Rules!$B$19,Rules!$B$18))))*IF(U82="Y",Rules!$B$22,1),2) -> 17 | AA82: =Y82-Z82 -> -0.5 | AB82: =IF(E82="Starter",IF(AA82<0,"Starter (under on purpose)","Starter too strong"),IF(ABS(AA82)<=Rules!$B$25,"Balanced",IF(AA82>0,"Over budget","Under budget"))) -> Balanced
A83: U24 | B83: Deflect | C83: Skill | D83: 0 | E83: Uncommon | F83: Guardian | G83: Gain 3 block. Retain. | H83: Gain 5 block. Retain. | K83: 3 | V83: Y | Y83: =ROUND((I83*Rules!$B$28+J83*Rules!$B$28*Rules!$B$24+K83*Rules!$B$29+L83*Rules!$B$30+M83*Rules!$B$31+N83*Rules!$B$32+(O83*Rules!$B$33+P83*Rules!$B$34+Q83*Rules!$B$35)*IF(R83="Y",Rules!$B$24,1)+S83*Rules!$B$36-T83*Rules!$B$37+IF(V83="Y",Rules!$B$38,0)+W83)*IF(C83="Power",Rules!$B$23,1),2) -> 5.6 | Z83: =ROUND((D83*Rules!$B$16+Rules!$B$17+IF(E83="Legendary",Rules!$B$21,IF(E83="Rare",Rules!$B$20,IF(E83="Uncommon",Rules!$B$19,Rules!$B$18))))*IF(U83="Y",Rules!$B$22,1),2) -> 5 | AA83: =Y83-Z83 -> 0.6 | AB83: =IF(E83="Starter",IF(AA83<0,"Starter (under on purpose)","Starter too strong"),IF(ABS(AA83)<=Rules!$B$25,"Balanced",IF(AA83>0,"Over budget","Under budget"))) -> Balanced
A84: U25 | B84: Shield Throw | C84: Attack | D84: 1 | E84: Uncommon | F84: Guardian | G84: Deal 6 damage to ALL enemies. Gain 2 block. | H84: Deal 8 damage to ALL enemies. Gain 3 block. | J84: 6 | K84: 2 | Y84: =ROUND((I84*Rules!$B$28+J84*Rules!$B$28*Rules!$B$24+K84*Rules!$B$29+L84*Rules!$B$30+M84*Rules!$B$31+N84*Rules!$B$32+(O84*Rules!$B$33+P84*Rules!$B$34+Q84*Rules!$B$35)*IF(R84="Y",Rules!$B$24,1)+S84*Rules!$B$36-T84*Rules!$B$37+IF(V84="Y",Rules!$B$38,0)+W84)*IF(C84="Power",Rules!$B$23,1),2) -> 11.4 | Z84: =ROUND((D84*Rules!$B$16+Rules!$B$17+IF(E84="Legendary",Rules!$B$21,IF(E84="Rare",Rules!$B$20,IF(E84="Uncommon",Rules!$B$19,Rules!$B$18))))*IF(U84="Y",Rules!$B$22,1),2) -> 11 | AA84: =Y84-Z84 -> 0.4 | AB84: =IF(E84="Starter",IF(AA84<0,"Starter (under on purpose)","Starter too strong"),IF(ABS(AA84)<=Rules!$B$25,"Balanced",IF(AA84>0,"Over budget","Under budget"))) -> Balanced
A85: U26 | B85: Stone Skin | C85: Skill | D85: 1 | E85: Uncommon | F85: Guardian | G85: Gain 8 block. Retain. | H85: Gain 11 block. Retain. | K85: 8 | V85: Y | Y85: =ROUND((I85*Rules!$B$28+J85*Rules!$B$28*Rules!$B$24+K85*Rules!$B$29+L85*Rules!$B$30+M85*Rules!$B$31+N85*Rules!$B$32+(O85*Rules!$B$33+P85*Rules!$B$34+Q85*Rules!$B$35)*IF(R85="Y",Rules!$B$24,1)+S85*Rules!$B$36-T85*Rules!$B$37+IF(V85="Y",Rules!$B$38,0)+W85)*IF(C85="Power",Rules!$B$23,1),2) -> 11.6 | Z85: =ROUND((D85*Rules!$B$16+Rules!$B$17+IF(E85="Legendary",Rules!$B$21,IF(E85="Rare",Rules!$B$20,IF(E85="Uncommon",Rules!$B$19,Rules!$B$18))))*IF(U85="Y",Rules!$B$22,1),2) -> 11 | AA85: =Y85-Z85 -> 0.6 | AB85: =IF(E85="Starter",IF(AA85<0,"Starter (under on purpose)","Starter too strong"),IF(ABS(AA85)<=Rules!$B$25,"Balanced",IF(AA85>0,"Over budget","Under budget"))) -> Balanced
A86: U27 | B86: Bastion | C86: Skill | D86: 2 | E86: Uncommon | F86: Guardian | G86: Gain 8 block. Apply 2 Weak. | H86: Gain 11 block. Apply 2 Weak. | K86: 8 | O86: 2 | Y86: =ROUND((I86*Rules!$B$28+J86*Rules!$B$28*Rules!$B$24+K86*Rules!$B$29+L86*Rules!$B$30+M86*Rules!$B$31+N86*Rules!$B$32+(O86*Rules!$B$33+P86*Rules!$B$34+Q86*Rules!$B$35)*IF(R86="Y",Rules!$B$24,1)+S86*Rules!$B$36-T86*Rules!$B$37+IF(V86="Y",Rules!$B$38,0)+W86)*IF(C86="Power",Rules!$B$23,1),2) -> 15.6 | Z86: =ROUND((D86*Rules!$B$16+Rules!$B$17+IF(E86="Legendary",Rules!$B$21,IF(E86="Rare",Rules!$B$20,IF(E86="Uncommon",Rules!$B$19,Rules!$B$18))))*IF(U86="Y",Rules!$B$22,1),2) -> 17 | AA86: =Y86-Z86 -> -1.4 | AB86: =IF(E86="Starter",IF(AA86<0,"Starter (under on purpose)","Starter too strong"),IF(ABS(AA86)<=Rules!$B$25,"Balanced",IF(AA86>0,"Over budget","Under budget"))) -> Balanced
A87: U28 | B87: Toxic Aura | C87: Power | D87: 1 | E87: Uncommon | F87: Venom | G87: At the start of your turn, apply 1 Poison to ALL enemies. | H87: At the start of your turn, apply 2 Poison to ALL enemies. | Q87: 1 | R87: Y | W87: 3.25 | X87: Reuses Black Plague's effect at a lower amount | Y87: =ROUND((I87*Rules!$B$28+J87*Rules!$B$28*Rules!$B$24+K87*Rules!$B$29+L87*Rules!$B$30+M87*Rules!$B$31+N87*Rules!$B$32+(O87*Rules!$B$33+P87*Rules!$B$34+Q87*Rules!$B$35)*IF(R87="Y",Rules!$B$24,1)+S87*Rules!$B$36-T87*Rules!$B$37+IF(V87="Y",Rules!$B$38,0)+W87)*IF(C87="Power",Rules!$B$23,1),2) -> 11 | Z87: =ROUND((D87*Rules!$B$16+Rules!$B$17+IF(E87="Legendary",Rules!$B$21,IF(E87="Rare",Rules!$B$20,IF(E87="Uncommon",Rules!$B$19,Rules!$B$18))))*IF(U87="Y",Rules!$B$22,1),2) -> 11 | AA87: =Y87-Z87 -> 0 | AB87: =IF(E87="Starter",IF(AA87<0,"Starter (under on purpose)","Starter too strong"),IF(ABS(AA87)<=Rules!$B$25,"Balanced",IF(AA87>0,"Over budget","Under budget"))) -> Balanced
A88: U29 | B88: Bane | C88: Attack | D88: 1 | E88: Uncommon | F88: Venom | G88: Deal 7 damage. If the enemy is poisoned, deal 7 more. | H88: Deal 9 damage. If the enemy is poisoned, deal 9 more. | I88: 7 | W88: 4 | X88: NEW: bonus_if_status. Other: conditional 7 damage (~4) | Y88: =ROUND((I88*Rules!$B$28+J88*Rules!$B$28*Rules!$B$24+K88*Rules!$B$29+L88*Rules!$B$30+M88*Rules!$B$31+N88*Rules!$B$32+(O88*Rules!$B$33+P88*Rules!$B$34+Q88*Rules!$B$35)*IF(R88="Y",Rules!$B$24,1)+S88*Rules!$B$36-T88*Rules!$B$37+IF(V88="Y",Rules!$B$38,0)+W88)*IF(C88="Power",Rules!$B$23,1),2) -> 11 | Z88: =ROUND((D88*Rules!$B$16+Rules!$B$17+IF(E88="Legendary",Rules!$B$21,IF(E88="Rare",Rules!$B$20,IF(E88="Uncommon",Rules!$B$19,Rules!$B$18))))*IF(U88="Y",Rules!$B$22,1),2) -> 11 | AA88: =Y88-Z88 -> 0 | AB88: =IF(E88="Starter",IF(AA88<0,"Starter (under on purpose)","Starter too strong"),IF(ABS(AA88)<=Rules!$B$25,"Balanced",IF(AA88>0,"Over budget","Under budget"))) -> Balanced
A89: U30 | B89: Corrosive Blade | C89: Attack | D89: 2 | E89: Uncommon | F89: Venom | G89: Deal 6 damage. Apply 7 Poison. | H89: Deal 8 damage. Apply 10 Poison. | I89: 6 | Q89: 7 | Y89: =ROUND((I89*Rules!$B$28+J89*Rules!$B$28*Rules!$B$24+K89*Rules!$B$29+L89*Rules!$B$30+M89*Rules!$B$31+N89*Rules!$B$32+(O89*Rules!$B$33+P89*Rules!$B$34+Q89*Rules!$B$35)*IF(R89="Y",Rules!$B$24,1)+S89*Rules!$B$36-T89*Rules!$B$37+IF(V89="Y",Rules!$B$38,0)+W89)*IF(C89="Power",Rules!$B$23,1),2) -> 16.5 | Z89: =ROUND((D89*Rules!$B$16+Rules!$B$17+IF(E89="Legendary",Rules!$B$21,IF(E89="Rare",Rules!$B$20,IF(E89="Uncommon",Rules!$B$19,Rules!$B$18))))*IF(U89="Y",Rules!$B$22,1),2) -> 17 | AA89: =Y89-Z89 -> -0.5 | AB89: =IF(E89="Starter",IF(AA89<0,"Starter (under on purpose)","Starter too strong"),IF(ABS(AA89)<=Rules!$B$25,"Balanced",IF(AA89>0,"Over budget","Under budget"))) -> Balanced
A90: U31 | B90: Virulence | C90: Skill | D90: 1 | E90: Uncommon | F90: Venom | G90: Apply 3 Poison to ALL enemies. Draw 1 card. | H90: Apply 4 Poison to ALL enemies. Draw 1 card. | M90: 1 | Q90: 3 | R90: Y | Y90: =ROUND((I90*Rules!$B$28+J90*Rules!$B$28*Rules!$B$24+K90*Rules!$B$29+L90*Rules!$B$30+M90*Rules!$B$31+N90*Rules!$B$32+(O90*Rules!$B$33+P90*Rules!$B$34+Q90*Rules!$B$35)*IF(R90="Y",Rules!$B$24,1)+S90*Rules!$B$36-T90*Rules!$B$37+IF(V90="Y",Rules!$B$38,0)+W90)*IF(C90="Power",Rules!$B$23,1),2) -> 10.75 | Z90: =ROUND((D90*Rules!$B$16+Rules!$B$17+IF(E90="Legendary",Rules!$B$21,IF(E90="Rare",Rules!$B$20,IF(E90="Uncommon",Rules!$B$19,Rules!$B$18))))*IF(U90="Y",Rules!$B$22,1),2) -> 11 | AA90: =Y90-Z90 -> -0.25 | AB90: =IF(E90="Starter",IF(AA90<0,"Starter (under on purpose)","Starter too strong"),IF(ABS(AA90)<=Rules!$B$25,"Balanced",IF(AA90>0,"Over budget","Under budget"))) -> Balanced
A91: U32 | B91: Bottled Plague | C91: Skill | D91: 0 | E91: Uncommon | F91: Venom | G91: Apply 3 Poison. Retain. | H91: Apply 5 Poison. Retain. | Q91: 3 | V91: Y | Y91: =ROUND((I91*Rules!$B$28+J91*Rules!$B$28*Rules!$B$24+K91*Rules!$B$29+L91*Rules!$B$30+M91*Rules!$B$31+N91*Rules!$B$32+(O91*Rules!$B$33+P91*Rules!$B$34+Q91*Rules!$B$35)*IF(R91="Y",Rules!$B$24,1)+S91*Rules!$B$36-T91*Rules!$B$37+IF(V91="Y",Rules!$B$38,0)+W91)*IF(C91="Power",Rules!$B$23,1),2) -> 6.5 | Z91: =ROUND((D91*Rules!$B$16+Rules!$B$17+IF(E91="Legendary",Rules!$B$21,IF(E91="Rare",Rules!$B$20,IF(E91="Uncommon",Rules!$B$19,Rules!$B$18))))*IF(U91="Y",Rules!$B$22,1),2) -> 5 | AA91: =Y91-Z91 -> 1.5 | AB91: =IF(E91="Starter",IF(AA91<0,"Starter (under on purpose)","Starter too strong"),IF(ABS(AA91)<=Rules!$B$25,"Balanced",IF(AA91>0,"Over budget","Under budget"))) -> Balanced
A92: U33 | B92: Toxic Shell | C92: Skill | D92: 1 | E92: Uncommon | F92: Venom | G92: Gain 5 block. Apply 3 Poison. | H92: Gain 7 block. Apply 4 Poison. | K92: 5 | Q92: 3 | Y92: =ROUND((I92*Rules!$B$28+J92*Rules!$B$28*Rules!$B$24+K92*Rules!$B$29+L92*Rules!$B$30+M92*Rules!$B$31+N92*Rules!$B$32+(O92*Rules!$B$33+P92*Rules!$B$34+Q92*Rules!$B$35)*IF(R92="Y",Rules!$B$24,1)+S92*Rules!$B$36-T92*Rules!$B$37+IF(V92="Y",Rules!$B$38,0)+W92)*IF(C92="Power",Rules!$B$23,1),2) -> 10.5 | Z92: =ROUND((D92*Rules!$B$16+Rules!$B$17+IF(E92="Legendary",Rules!$B$21,IF(E92="Rare",Rules!$B$20,IF(E92="Uncommon",Rules!$B$19,Rules!$B$18))))*IF(U92="Y",Rules!$B$22,1),2) -> 11 | AA92: =Y92-Z92 -> -0.5 | AB92: =IF(E92="Starter",IF(AA92<0,"Starter (under on purpose)","Starter too strong"),IF(ABS(AA92)<=Rules!$B$25,"Balanced",IF(AA92>0,"Over budget","Under budget"))) -> Balanced
A93: U34 | B93: Venom Burst | C93: Attack | D93: 1 | E93: Uncommon | F93: Venom | G93: Deal damage equal to the enemy's Poison. | H93: Costs 0. Deal damage equal to the enemy's Poison. | W93: 10 | X93: NEW: damage_equals_status (Poison). PLAYTEST: scales with Poison | Y93: =ROUND((I93*Rules!$B$28+J93*Rules!$B$28*Rules!$B$24+K93*Rules!$B$29+L93*Rules!$B$30+M93*Rules!$B$31+N93*Rules!$B$32+(O93*Rules!$B$33+P93*Rules!$B$34+Q93*Rules!$B$35)*IF(R93="Y",Rules!$B$24,1)+S93*Rules!$B$36-T93*Rules!$B$37+IF(V93="Y",Rules!$B$38,0)+W93)*IF(C93="Power",Rules!$B$23,1),2) -> 10 | Z93: =ROUND((D93*Rules!$B$16+Rules!$B$17+IF(E93="Legendary",Rules!$B$21,IF(E93="Rare",Rules!$B$20,IF(E93="Uncommon",Rules!$B$19,Rules!$B$18))))*IF(U93="Y",Rules!$B$22,1),2) -> 11 | AA93: =Y93-Z93 -> -1 | AB93: =IF(E93="Starter",IF(AA93<0,"Starter (under on purpose)","Starter too strong"),IF(ABS(AA93)<=Rules!$B$25,"Balanced",IF(AA93>0,"Over budget","Under budget"))) -> Balanced
A94: U35 | B94: Reconnaissance | C94: Skill | D94: 1 | E94: Uncommon | F94: Tactician | G94: Draw 2 cards. Apply 1 Vulnerable to ALL enemies. | H94: Draw 3 cards. Apply 1 Vulnerable to ALL enemies. | M94: 2 | P94: 1 | R94: Y | Y94: =ROUND((I94*Rules!$B$28+J94*Rules!$B$28*Rules!$B$24+K94*Rules!$B$29+L94*Rules!$B$30+M94*Rules!$B$31+N94*Rules!$B$32+(O94*Rules!$B$33+P94*Rules!$B$34+Q94*Rules!$B$35)*IF(R94="Y",Rules!$B$24,1)+S94*Rules!$B$36-T94*Rules!$B$37+IF(V94="Y",Rules!$B$38,0)+W94)*IF(C94="Power",Rules!$B$23,1),2) -> 12.5 | Z94: =ROUND((D94*Rules!$B$16+Rules!$B$17+IF(E94="Legendary",Rules!$B$21,IF(E94="Rare",Rules!$B$20,IF(E94="Uncommon",Rules!$B$19,Rules!$B$18))))*IF(U94="Y",Rules!$B$22,1),2) -> 11 | AA94: =Y94-Z94 -> 1.5 | AB94: =IF(E94="Starter",IF(AA94<0,"Starter (under on purpose)","Starter too strong"),IF(ABS(AA94)<=Rules!$B$25,"Balanced",IF(AA94>0,"Over budget","Under budget"))) -> Balanced
A95: U36 | B95: Tactical Retreat | C95: Skill | D95: 1 | E95: Uncommon | F95: Tactician | G95: Gain 4 block. Next turn, gain 1 energy. | H95: Gain 7 block. Next turn, gain 1 energy. | K95: 4 | N95: 1 | X95: NEW: energy_next_turn (priced as energy) | Y95: =ROUND((I95*Rules!$B$28+J95*Rules!$B$28*Rules!$B$24+K95*Rules!$B$29+L95*Rules!$B$30+M95*Rules!$B$31+N95*Rules!$B$32+(O95*Rules!$B$33+P95*Rules!$B$34+Q95*Rules!$B$35)*IF(R95="Y",Rules!$B$24,1)+S95*Rules!$B$36-T95*Rules!$B$37+IF(V95="Y",Rules!$B$38,0)+W95)*IF(C95="Power",Rules!$B$23,1),2) -> 10.8 | Z95: =ROUND((D95*Rules!$B$16+Rules!$B$17+IF(E95="Legendary",Rules!$B$21,IF(E95="Rare",Rules!$B$20,IF(E95="Uncommon",Rules!$B$19,Rules!$B$18))))*IF(U95="Y",Rules!$B$22,1),2) -> 11 | AA95: =Y95-Z95 -> -0.2 | AB95: =IF(E95="Starter",IF(AA95<0,"Starter (under on purpose)","Starter too strong"),IF(ABS(AA95)<=Rules!$B$25,"Balanced",IF(AA95>0,"Over budget","Under budget"))) -> Balanced
A96: U37 | B96: Weak Point | C96: Attack | D96: 2 | E96: Uncommon | F96: Tactician | G96: Deal 8 damage. Apply 2 Vulnerable and 1 Weak. | H96: Deal 11 damage. Apply 3 Vulnerable and 1 Weak. | I96: 8 | O96: 1 | P96: 2 | Y96: =ROUND((I96*Rules!$B$28+J96*Rules!$B$28*Rules!$B$24+K96*Rules!$B$29+L96*Rules!$B$30+M96*Rules!$B$31+N96*Rules!$B$32+(O96*Rules!$B$33+P96*Rules!$B$34+Q96*Rules!$B$35)*IF(R96="Y",Rules!$B$24,1)+S96*Rules!$B$36-T96*Rules!$B$37+IF(V96="Y",Rules!$B$38,0)+W96)*IF(C96="Power",Rules!$B$23,1),2) -> 17 | Z96: =ROUND((D96*Rules!$B$16+Rules!$B$17+IF(E96="Legendary",Rules!$B$21,IF(E96="Rare",Rules!$B$20,IF(E96="Uncommon",Rules!$B$19,Rules!$B$18))))*IF(U96="Y",Rules!$B$22,1),2) -> 17 | AA96: =Y96-Z96 -> 0 | AB96: =IF(E96="Starter",IF(AA96<0,"Starter (under on purpose)","Starter too strong"),IF(ABS(AA96)<=Rules!$B$25,"Balanced",IF(AA96>0,"Over budget","Under budget"))) -> Balanced
A97: U38 | B97: Overwhelm | C97: Skill | D97: 2 | E97: Uncommon | F97: Tactician | G97: Apply 2 Weak and 2 Vulnerable to ALL enemies. | H97: Apply 3 Weak and 3 Vulnerable to ALL enemies. | O97: 2 | P97: 2 | R97: Y | Y97: =ROUND((I97*Rules!$B$28+J97*Rules!$B$28*Rules!$B$24+K97*Rules!$B$29+L97*Rules!$B$30+M97*Rules!$B$31+N97*Rules!$B$32+(O97*Rules!$B$33+P97*Rules!$B$34+Q97*Rules!$B$35)*IF(R97="Y",Rules!$B$24,1)+S97*Rules!$B$36-T97*Rules!$B$37+IF(V97="Y",Rules!$B$38,0)+W97)*IF(C97="Power",Rules!$B$23,1),2) -> 18 | Z97: =ROUND((D97*Rules!$B$16+Rules!$B$17+IF(E97="Legendary",Rules!$B$21,IF(E97="Rare",Rules!$B$20,IF(E97="Uncommon",Rules!$B$19,Rules!$B$18))))*IF(U97="Y",Rules!$B$22,1),2) -> 17 | AA97: =Y97-Z97 -> 1 | AB97: =IF(E97="Starter",IF(AA97<0,"Starter (under on purpose)","Starter too strong"),IF(ABS(AA97)<=Rules!$B$25,"Balanced",IF(AA97>0,"Over budget","Under budget"))) -> Balanced
A98: U39 | B98: Battle Rhythm | C98: Skill | D98: 1 | E98: Uncommon | F98: Tactician | G98: Draw 1 card. Next turn, gain 1 energy. Retain. | H98: Draw 2 cards. Next turn, gain 1 energy. Retain. | M98: 1 | N98: 1 | V98: Y | X98: Uses energy_next_turn | Y98: =ROUND((I98*Rules!$B$28+J98*Rules!$B$28*Rules!$B$24+K98*Rules!$B$29+L98*Rules!$B$30+M98*Rules!$B$31+N98*Rules!$B$32+(O98*Rules!$B$33+P98*Rules!$B$34+Q98*Rules!$B$35)*IF(R98="Y",Rules!$B$24,1)+S98*Rules!$B$36-T98*Rules!$B$37+IF(V98="Y",Rules!$B$38,0)+W98)*IF(C98="Power",Rules!$B$23,1),2) -> 12 | Z98: =ROUND((D98*Rules!$B$16+Rules!$B$17+IF(E98="Legendary",Rules!$B$21,IF(E98="Rare",Rules!$B$20,IF(E98="Uncommon",Rules!$B$19,Rules!$B$18))))*IF(U98="Y",Rules!$B$22,1),2) -> 11 | AA98: =Y98-Z98 -> 1 | AB98: =IF(E98="Starter",IF(AA98<0,"Starter (under on purpose)","Starter too strong"),IF(ABS(AA98)<=Rules!$B$25,"Balanced",IF(AA98>0,"Over budget","Under budget"))) -> Balanced
A99: U40 | B99: Momentum | C99: Skill | D99: 1 | E99: Uncommon | F99: Tactician | G99: Draw 2 cards. Retain. | H99: Draw 3 cards. Retain. | M99: 2 | V99: Y | Y99: =ROUND((I99*Rules!$B$28+J99*Rules!$B$28*Rules!$B$24+K99*Rules!$B$29+L99*Rules!$B$30+M99*Rules!$B$31+N99*Rules!$B$32+(O99*Rules!$B$33+P99*Rules!$B$34+Q99*Rules!$B$35)*IF(R99="Y",Rules!$B$24,1)+S99*Rules!$B$36-T99*Rules!$B$37+IF(V99="Y",Rules!$B$38,0)+W99)*IF(C99="Power",Rules!$B$23,1),2) -> 10 | Z99: =ROUND((D99*Rules!$B$16+Rules!$B$17+IF(E99="Legendary",Rules!$B$21,IF(E99="Rare",Rules!$B$20,IF(E99="Uncommon",Rules!$B$19,Rules!$B$18))))*IF(U99="Y",Rules!$B$22,1),2) -> 11 | AA99: =Y99-Z99 -> -1 | AB99: =IF(E99="Starter",IF(AA99<0,"Starter (under on purpose)","Starter too strong"),IF(ABS(AA99)<=Rules!$B$25,"Balanced",IF(AA99>0,"Over budget","Under budget"))) -> Balanced
A100: R01 | B100: Thorn Armor | C100: Power | D100: 2 | E100: Rare | F100: Guardian | G100: Whenever you gain block, deal 3 damage to a random enemy. | H100: Whenever you gain block, deal 5 damage to a random enemy. | W100: 9.5 | X100: PLAYTEST: ~2 block cards per turn | Y100: =ROUND((I100*Rules!$B$28+J100*Rules!$B$28*Rules!$B$24+K100*Rules!$B$29+L100*Rules!$B$30+M100*Rules!$B$31+N100*Rules!$B$32+(O100*Rules!$B$33+P100*Rules!$B$34+Q100*Rules!$B$35)*IF(R100="Y",Rules!$B$24,1)+S100*Rules!$B$36-T100*Rules!$B$37+IF(V100="Y",Rules!$B$38,0)+W100)*IF(C100="Power",Rules!$B$23,1),2) -> 19 | Z100: =ROUND((D100*Rules!$B$16+Rules!$B$17+IF(E100="Legendary",Rules!$B$21,IF(E100="Rare",Rules!$B$20,IF(E100="Uncommon",Rules!$B$19,Rules!$B$18))))*IF(U100="Y",Rules!$B$22,1),2) -> 19 | AA100: =Y100-Z100 -> 0 | AB100: =IF(E100="Starter",IF(AA100<0,"Starter (under on purpose)","Starter too strong"),IF(ABS(AA100)<=Rules!$B$25,"Balanced",IF(AA100>0,"Over budget","Under budget"))) -> Balanced
...

Sheet Summary
A1: Set Summary
A3: Archetype | B3: Starter | C3: Common | D3: Uncommon | E3: Rare | F3: Legendary | G3: Total
A4: Neutral | B4: =COUNTIFS(Cards!$F$2:$F$400,$A4,Cards!$E$2:$E$400,B$3) -> 3 | C4: =COUNTIFS(Cards!$F$2:$F$400,$A4,Cards!$E$2:$E$400,C$3) -> 7 | D4: =COUNTIFS(Cards!$F$2:$F$400,$A4,Cards!$E$2:$E$400,D$3) -> 3 | E4: =COUNTIFS(Cards!$F$2:$F$400,$A4,Cards!$E$2:$E$400,E$3) -> 3 | F4: =COUNTIFS(Cards!$F$2:$F$400,$A4,Cards!$E$2:$E$400,F$3) -> 0 | G4: =SUM(B4:F4) -> 16
A5: Brawler | B5: =COUNTIFS(Cards!$F$2:$F$400,$A5,Cards!$E$2:$E$400,B$3) -> 0 | C5: =COUNTIFS(Cards!$F$2:$F$400,$A5,Cards!$E$2:$E$400,C$3) -> 12 | D5: =COUNTIFS(Cards!$F$2:$F$400,$A5,Cards!$E$2:$E$400,D$3) -> 9 | E5: =COUNTIFS(Cards!$F$2:$F$400,$A5,Cards!$E$2:$E$400,E$3) -> 5 | F5: =COUNTIFS(Cards!$F$2:$F$400,$A5,Cards!$E$2:$E$400,F$3) -> 2 | G5: =SUM(B5:F5) -> 28
A6: Guardian | B6: =COUNTIFS(Cards!$F$2:$F$400,$A6,Cards!$E$2:$E$400,B$3) -> 0 | C6: =COUNTIFS(Cards!$F$2:$F$400,$A6,Cards!$E$2:$E$400,C$3) -> 13 | D6: =COUNTIFS(Cards!$F$2:$F$400,$A6,Cards!$E$2:$E$400,D$3) -> 9 | E6: =COUNTIFS(Cards!$F$2:$F$400,$A6,Cards!$E$2:$E$400,E$3) -> 4 | F6: =COUNTIFS(Cards!$F$2:$F$400,$A6,Cards!$E$2:$E$400,F$3) -> 2 | G6: =SUM(B6:F6) -> 28
A7: Venom | B7: =COUNTIFS(Cards!$F$2:$F$400,$A7,Cards!$E$2:$E$400,B$3) -> 0 | C7: =COUNTIFS(Cards!$F$2:$F$400,$A7,Cards!$E$2:$E$400,C$3) -> 11 | D7: =COUNTIFS(Cards!$F$2:$F$400,$A7,Cards!$E$2:$E$400,D$3) -> 10 | E7: =COUNTIFS(Cards!$F$2:$F$400,$A7,Cards!$E$2:$E$400,E$3) -> 5 | F7: =COUNTIFS(Cards!$F$2:$F$400,$A7,Cards!$E$2:$E$400,F$3) -> 2 | G7: =SUM(B7:F7) -> 28
A8: Tactician | B8: =COUNTIFS(Cards!$F$2:$F$400,$A8,Cards!$E$2:$E$400,B$3) -> 0 | C8: =COUNTIFS(Cards!$F$2:$F$400,$A8,Cards!$E$2:$E$400,C$3) -> 12 | D8: =COUNTIFS(Cards!$F$2:$F$400,$A8,Cards!$E$2:$E$400,D$3) -> 9 | E8: =COUNTIFS(Cards!$F$2:$F$400,$A8,Cards!$E$2:$E$400,E$3) -> 5 | F8: =COUNTIFS(Cards!$F$2:$F$400,$A8,Cards!$E$2:$E$400,F$3) -> 2 | G8: =SUM(B8:F8) -> 28
A9: Total | B9: =SUM(B4:B8) -> 3 | C9: =SUM(C4:C8) -> 55 | D9: =SUM(D4:D8) -> 40 | E9: =SUM(E4:E8) -> 22 | F9: =SUM(F4:F8) -> 8 | G9: =SUM(G4:G8) -> 128
A11: Balance status
A12: Balanced | B12: =COUNTIF(Cards!$AB$2:$AB$400,A12) -> 125
A13: Over budget | B13: =COUNTIF(Cards!$AB$2:$AB$400,A13) -> 0
A14: Under budget | B14: =COUNTIF(Cards!$AB$2:$AB$400,A14) -> 0
A15: Starter (under on purpose) | B15: =COUNTIF(Cards!$AB$2:$AB$400,A15) -> 3
A17: Type (excluding starters)
A18: Attack | B18: =COUNTIFS(Cards!$C$2:$C$400,A18,Cards!$E$2:$E$400,"<>Starter") -> 46
A19: Skill | B19: =COUNTIFS(Cards!$C$2:$C$400,A19,Cards!$E$2:$E$400,"<>Starter") -> 63
A20: Power | B20: =COUNTIFS(Cards!$C$2:$C$400,A20,Cards!$E$2:$E$400,"<>Starter") -> 16
A22: Starter deck
A23: Strike | B23: 5
A24: Defend | B24: 4
A25: Lantern Bash | B25: 1
A26: Total | B26: =SUM(B23:B25) -> 10
A28: Reward odds per card offered (normal fights)
A29: Common | B29: 0.6
A30: Uncommon | B30: 0.31
A31: Rare | B31: 0.07
A32: Legendary | B32: 0.02
A33: Total | B33: =SUM(B29:B32) -> 1
A35: Elite and boss rewards
A36: After an elite or the boss, one of the 3 choices is always a Legendary the player doesn't own (Unique: max 1 copy per deck).

Sheet Keywords
A1: Keywords (show as tap-to-explain on cards)
A3: Keyword | B3: Rule | C3: Who implements
A4: Block | B4: Prevents damage. All block is removed at the start of your next turn. | C4: Role 1
A5: Heal | B5: Restore HP, up to max HP. | C5: Role 1
A6: Poison | B6: At the start of the poisoned creature's turn, it loses HP equal to its Poison, then Poison goes down by 1. | C6: Role 1
A7: Weak | B7: Deals 25% less attack damage. Lasts the listed number of turns. | C7: Role 1
A8: Vulnerable | B8: Takes 50% more attack damage. Lasts the listed number of turns. | C8: Role 1
A9: Strength | B9: Each attack hit deals +1 damage per Strength. Lasts the whole fight. | C9: Role 1
A10: Exhaust | B10: After playing, remove this card from your deck for the rest of the fight (it returns next fight). | C10: Role 2
A11: Power | B11: Stays in play for the rest of the fight instead of going to the discard pile. | C11: Role 2
A12: ALL enemies | B12: Hits every enemy in the fight. | C12: Role 1
A13: Intent | B13: Enemies show what they'll do next turn. Some cards (Parry, Rebuke) check it. | C13: Role 1 + Role 3
A14: Discard | B14: Choose a card from your hand to put in the discard pile. | C14: Role 2 + Role 3
... A17: Invulnerable | B17: NEW. You take no damage until your next turn. | C17: Role 1

Sheet New Mechanics
A1: New mechanics in the alpha set (for the code phase)
A2: Commons and Uncommons use only 7 of these; most are on Rares and Legendaries.
A4: Mechanic / code op | B4: What it does | C4: Cards that use it | D4: Who implements
A5: Retain (keyword) | B5: Card stays in hand at end of turn. | C5: Torchlight, Hunker Down, Poison Shank, Prepared Strike, Deflect, Stone Skin, Bottled Plague, Battle Rhythm, Momentum, Battle Plan | D5: Role 2
A6: Unique (keyword) | B6: Max one copy per deck; reward generator skips Uniques you own. | C6: All 8 Legendaries | D6: Role 2 + Role 4
A7: Legendary rarity | B7: +6 budget; 2% reward odds; guaranteed choice after elites/boss. | C7: All 8 Legendaries | D7: Role 2 + Role 4
A8: damage_equals_block | B8: Deal damage equal to your current block. | C8: Buckler Bash | D8: Role 1
A9: if_intent on a status | B9: Apply a status only if the enemy intends to attack. | C9: Rebuke | D9: Role 1
A10: energy_next_turn | B10: Gain energy at the start of your next turn. | C10: Tactical Retreat, Battle Rhythm | D10: Role 1
A11: multiply_block | B11: Multiply your current block. | C11: Entrench | D11: Role 1
A12: bonus_if_status | B12: Extra damage if the target has a status. | C12: Bane (Poison), Exploit Weakness (Vulnerable) | D12: Role 1
A13: damage_equals_status | B13: Deal damage equal to the target's Poison. | C13: Venom Burst | D13: Role 1
A14: power: draw_per_turn | B14: Draw extra cards at the start of each turn. | C14: Map of the Depths, Explorer's Kit, Grand Strategist | D14: Role 1 + Role 2
A15: power: strength_per_turn | B15: Gain Strength at the start of each turn. | C15: Bloodlust | D15: Role 1
... A24: Reused existing effects | B24: No new code: multiply_status (Limit Break, Pandemic, Plaguebearer's Kiss), random_enemy target (Wild Swing), Black Plague at a lower amount (Toxic Aura), Iron Skin/Berserker Rage on new Powers. | C24: Several | D24: —
